{"posts":[{"actor_id":"1591617373","post_id":"1540549221_10204209591110224","comment_info":{"can_comment":"1","comment_count":"0","comment_order":"chronological"},"created_time":"1407701720","is_popular":"","likes":{"href":"https:\/\/www.facebook.com\/browse\/likes\/?id=10204209591110224","count":"0","sample":"","friends":"","user_likes":"0","can_like":"1"},"permalink":"https:\/\/www.facebook.com\/l.marchegiani\/posts\/10204209591110224","privacy":{"value":""},"share_count":"0","source_id":"1540549221","tagged_ids":"","type":"","updated_time":"1407701720","with_tags":""},{"actor_id":"1540549221","post_id":"1540549221_10203471421816453","comment_info":{"can_comment":"1","comment_count":"5","comment_order":"chronological"},"created_time":"1398860549","is_popular":"","likes":{"href":"https:\/\/www.facebook.com\/browse\/likes\/?id=10203471421656449","count":"14","sample":["100004986124368","1451275945","1663545275","100006337893086"],"friends":"","user_likes":"0","can_like":"1"},"permalink":"https:\/\/www.facebook.com\/photo.php?fbid=10203471421656449&set=p.10203471421656449&type=1&relevant_count=1","privacy":{"value":""},"share_count":"0","source_id":"1540549221","tagged_ids":"","type":"","updated_time":"1398959229","with_tags":""},{"actor_id":"1036958957","post_id":"1540549221_10203155324874227","comment_info":{"can_comment":"1","comment_count":"4","comment_order":"chronological"},"created_time":"1394884447","is_popular":"","likes":{"sample":"","friends":"","can_like":"0"},"permalink":"","privacy":{"value":""},"share_count":"0","source_id":"1540549221","tagged_ids":["4804242","1540549221","1630352083","1521777164","1549957566","1582551301","1558402286"],"type":"","updated_time":"1394884447","with_tags":""},{"actor_id":"1360823235","post_id":"1540549221_10203148582945683","comment_info":{"can_comment":"1","comment_count":"0","comment_order":"chronological"},"created_time":"1394779582","is_popular":"","likes":{"sample":"","friends":"","can_like":"0"},"permalink":"","privacy":{"value":""},"share_count":"0","source_id":"1540549221","tagged_ids":["526941127412842","1357224255","100004244312936","100000372190462","1663545275","100002842382911","1540549221","1521777164","1296489236"],"type":"","updated_time":"1394779582","with_tags":""},{"actor_id":"1391825494","post_id":"1540549221_10202968554685089","comment_info":{"can_comment":"1","comment_count":"0","comment_order":"chronological"},"created_time":"1392501806","is_popular":"","likes":{"sample":"","friends":"","can_like":"0"},"permalink":"","privacy":{"value":""},"share_count":"0","source_id":"1540549221","tagged_ids":["1540549221","1521777164","1630352083"],"type":"","updated_time":"1392501806","with_tags":""},{"actor_id":"1663545275","post_id":"1540549221_10202921463867848","comment_info":{"can_comment":"1","comment_count":"1","comment_order":"chronological"},"created_time":"1391971471","is_popular":"","likes":{"sample":"","friends":"","can_like":"0"},"permalink":"","privacy":{"value":""},"share_count":"0","source_id":"1540549221","tagged_ids":["1357224255","100002842382911","100004244312936","1624838138","1360823235","1540549221","1521777164","1510001394","1641434270","100000372190462"],"type":"","updated_time":"1391971471","with_tags":""},{"actor_id":"1641434270","post_id":"1540549221_10202626696618851","comment_info":{"can_comment":"1","comment_count":"2","comment_order":"chronological"},"created_time":"1388223052","is_popular":"","likes":{"sample":"","friends":"","can_like":"0"},"permalink":"","privacy":{"value":""},"share_count":"0","source_id":"1540549221","tagged_ids":["1357224255","1540549221"],"type":"","updated_time":"1388223052","with_tags":""},{"actor_id":"100000015531407","post_id":"1540549221_692517440758767","comment_info":{"can_comment":"1","comment_count":"0","comment_order":"chronological"},"created_time":"1383908594","is_popular":"","likes":{"href":"https:\/\/www.facebook.com\/browse\/likes\/?id=692517440758767","count":"0","sample":"","friends":"","user_likes":"0","can_like":"1"},"permalink":"https:\/\/www.facebook.com\/l.marchegiani\/posts\/692517440758767","privacy":{"value":""},"share_count":"0","source_id":"1540549221","tagged_ids":"","type":"","updated_time":"1383908594","with_tags":""},{"actor_id":"100000015531407","post_id":"1540549221_684236838253494","comment_info":{"can_comment":"1","comment_count":"0","comment_order":"chronological"},"created_time":"1382626213","is_popular":"","likes":{"href":"https:\/\/www.facebook.com\/browse\/likes\/?id=684236838253494","count":"0","sample":"","friends":"","user_likes":"0","can_like":"1"},"permalink":"https:\/\/www.facebook.com\/l.marchegiani\/posts\/684236838253494","privacy":{"value":""},"share_count":"0","source_id":"1540549221","tagged_ids":"","type":"","updated_time":"1382626213","with_tags":""},{"actor_id":"535081532","post_id":"1540549221_10202039741905350","comment_info":{"can_comment":"1","comment_count":"0","comment_order":"chronological"},"created_time":"1381891610","is_popular":"","likes":{"href":"https:\/\/www.facebook.com\/browse\/likes\/?id=10202039741905350","count":"0","sample":"","friends":"","user_likes":"0","can_like":"1"},"permalink":"https:\/\/www.facebook.com\/l.marchegiani\/posts\/10202039741905350","privacy":{"value":""},"share_count":"0","source_id":"1540549221","tagged_ids":"","type":"","updated_time":"1381891610","with_tags":""},{"actor_id":"4804242","post_id":"1540549221_10202038858323261","comment_info":{"can_comment":"1","comment_count":"0","comment_order":"chronological"},"created_time":"1381878329","is_popular":"","likes":{"href":"https:\/\/www.facebook.com\/browse\/likes\/?id=10202038858323261","count":"0","sample":"","friends":"","user_likes":"0","can_like":"1"},"permalink":"https:\/\/www.facebook.com\/l.marchegiani\/posts\/10202038858323261","privacy":{"value":""},"share_count":"0","source_id":"1540549221","tagged_ids":"","type":"","updated_time":"1381878329","with_tags":""},{"actor_id":"1529808257","post_id":"1540549221_10202038393951652","comment_info":{"can_comment":"1","comment_count":"0","comment_order":"chronological"},"created_time":"1381872461","is_popular":"","likes":{"href":"https:\/\/www.facebook.com\/browse\/likes\/?id=10202038393951652","count":"0","sample":"","friends":"","user_likes":"0","can_like":"1"},"permalink":"https:\/\/www.facebook.com\/l.marchegiani\/posts\/10202038393951652","privacy":{"value":""},"share_count":"0","source_id":"1540549221","tagged_ids":"","type":"","updated_time":"1381872461","with_tags":""},{"actor_id":"100000440114339","post_id":"1540549221_10202038123144882","comment_info":{"can_comment":"1","comment_count":"0","comment_order":"chronological"},"created_time":"1381870073","is_popular":"","likes":{"href":"https:\/\/www.facebook.com\/browse\/likes\/?id=10202038123144882","count":"0","sample":"","friends":"","user_likes":"0","can_like":"1"},"permalink":"https:\/\/www.facebook.com\/l.marchegiani\/posts\/10202038123144882","privacy":{"value":""},"share_count":"0","source_id":"1540549221","tagged_ids":"","type":"","updated_time":"1381870073","with_tags":""},{"actor_id":"100001156633827","post_id":"1540549221_10202037897059230","comment_info":{"can_comment":"1","comment_count":"0","comment_order":"chronological"},"created_time":"1381868057","is_popular":"","likes":{"href":"https:\/\/www.facebook.com\/browse\/likes\/?id=10202037897059230","count":"0","sample":"","friends":"","user_likes":"0","can_like":"1"},"permalink":"https:\/\/www.facebook.com\/l.marchegiani\/posts\/10202037897059230","privacy":{"value":""},"share_count":"0","source_id":"1540549221","tagged_ids":"","type":"","updated_time":"1381868057","with_tags":""},{"actor_id":"1216442611","post_id":"1540549221_10202037460528317","comment_info":{"can_comment":"1","comment_count":"0","comment_order":"chronological"},"created_time":"1381863351","is_popular":"","likes":{"href":"https:\/\/www.facebook.com\/browse\/likes\/?id=10202037460528317","count":"0","sample":"","friends":"","user_likes":"0","can_like":"1"},"permalink":"https:\/\/www.facebook.com\/l.marchegiani\/posts\/10202037460528317","privacy":{"value":""},"share_count":"0","source_id":"1540549221","tagged_ids":"","type":"","updated_time":"1381863351","with_tags":""},{"actor_id":"1635559094","post_id":"1540549221_10202036610747073","comment_info":{"can_comment":"1","comment_count":"0","comment_order":"chronological"},"created_time":"1381853709","is_popular":"","likes":{"href":"https:\/\/www.facebook.com\/browse\/likes\/?id=10202036610747073","count":"0","sample":"","friends":"","user_likes":"0","can_like":"1"},"permalink":"https:\/\/www.facebook.com\/l.marchegiani\/posts\/10202036610747073","privacy":{"value":""},"share_count":"0","source_id":"1540549221","tagged_ids":"","type":"","updated_time":"1381853709","with_tags":""},{"actor_id":"1384844499","post_id":"1540549221_10202035579521293","comment_info":{"can_comment":"1","comment_count":"0","comment_order":"chronological"},"created_time":"1381844490","is_popular":"","likes":{"href":"https:\/\/www.facebook.com\/browse\/likes\/?id=10202035579521293","count":"0","sample":"","friends":"","user_likes":"0","can_like":"1"},"permalink":"https:\/\/www.facebook.com\/l.marchegiani\/posts\/10202035579521293","privacy":{"value":""},"share_count":"0","source_id":"1540549221","tagged_ids":"","type":"","updated_time":"1381844490","with_tags":""},{"actor_id":"1591617373","post_id":"1540549221_10202033774996181","comment_info":{"can_comment":"1","comment_count":"0","comment_order":"chronological"},"created_time":"1381842856","is_popular":"","likes":{"href":"https:\/\/www.facebook.com\/browse\/likes\/?id=10202033774996181","count":"0","sample":"","friends":"","user_likes":"0","can_like":"1"},"permalink":"https:\/\/www.facebook.com\/l.marchegiani\/posts\/10202033774996181","privacy":{"value":""},"share_count":"0","source_id":"1540549221","tagged_ids":"","type":"","updated_time":"1381842856","with_tags":""},{"actor_id":"1619951245","post_id":"1540549221_10202033308464518","comment_info":{"can_comment":"1","comment_count":"0","comment_order":"chronological"},"created_time":"1381842601","is_popular":"","likes":{"href":"https:\/\/www.facebook.com\/browse\/likes\/?id=10202033308464518","count":"0","sample":"","friends":"","user_likes":"0","can_like":"1"},"permalink":"https:\/\/www.facebook.com\/l.marchegiani\/posts\/10202033308464518","privacy":{"value":""},"share_count":"0","source_id":"1540549221","tagged_ids":"","type":"","updated_time":"1381842601","with_tags":""},{"actor_id":"100001566763855","post_id":"1540549221_10202032840452818","comment_info":{"can_comment":"1","comment_count":"0","comment_order":"chronological"},"created_time":"1381842150","is_popular":"","likes":{"href":"https:\/\/www.facebook.com\/browse\/likes\/?id=10202032840452818","count":"0","sample":"","friends":"","user_likes":"0","can_like":"1"},"permalink":"https:\/\/www.facebook.com\/l.marchegiani\/posts\/10202032840452818","privacy":{"value":""},"share_count":"0","source_id":"1540549221","tagged_ids":"","type":"","updated_time":"1381842150","with_tags":""},{"actor_id":"1592164313","post_id":"1540549221_10202032781771351","comment_info":{"can_comment":"1","comment_count":"0","comment_order":"chronological"},"created_time":"1381841660","is_popular":"","likes":{"href":"https:\/\/www.facebook.com\/browse\/likes\/?id=10202032781771351","count":"0","sample":"","friends":"","user_likes":"0","can_like":"1"},"permalink":"https:\/\/www.facebook.com\/l.marchegiani\/posts\/10202032781771351","privacy":{"value":""},"share_count":"0","source_id":"1540549221","tagged_ids":"","type":"","updated_time":"1381841660","with_tags":""},{"actor_id":"1549957566","post_id":"1540549221_10202032379241288","comment_info":{"can_comment":"1","comment_count":"0","comment_order":"chronological"},"created_time":"1381840917","is_popular":"","likes":{"href":"https:\/\/www.facebook.com\/browse\/likes\/?id=10202032379241288","count":"0","sample":"","friends":"","user_likes":"0","can_like":"1"},"permalink":"https:\/\/www.facebook.com\/l.marchegiani\/posts\/10202032379241288","privacy":{"value":""},"share_count":"0","source_id":"1540549221","tagged_ids":"","type":"","updated_time":"1381840917","with_tags":""},{"actor_id":"1343226804","post_id":"1540549221_10202032347720500","comment_info":{"can_comment":"1","comment_count":"0","comment_order":"chronological"},"created_time":"1381840790","is_popular":"","likes":{"href":"https:\/\/www.facebook.com\/browse\/likes\/?id=10202032347720500","count":"0","sample":"","friends":"","user_likes":"0","can_like":"1"},"permalink":"https:\/\/www.facebook.com\/l.marchegiani\/posts\/10202032347720500","privacy":{"value":""},"share_count":"0","source_id":"1540549221","tagged_ids":"","type":"","updated_time":"1381840790","with_tags":""},{"actor_id":"1489583081","post_id":"1540549221_10202032300799327","comment_info":{"can_comment":"1","comment_count":"0","comment_order":"chronological"},"created_time":"1381840608","is_popular":"","likes":{"href":"https:\/\/www.facebook.com\/browse\/likes\/?id=10202032300799327","count":"0","sample":"","friends":"","user_likes":"0","can_like":"1"},"permalink":"https:\/\/www.facebook.com\/l.marchegiani\/posts\/10202032300799327","privacy":{"value":""},"share_count":"0","source_id":"1540549221","tagged_ids":"","type":"","updated_time":"1381840608","with_tags":""},{"actor_id":"100000264283314","post_id":"1540549221_10202032288159011","comment_info":{"can_comment":"1","comment_count":"0","comment_order":"chronological"},"created_time":"1381840508","is_popular":"","likes":{"href":"https:\/\/www.facebook.com\/browse\/likes\/?id=10202032288159011","count":"0","sample":"","friends":"","user_likes":"0","can_like":"1"},"permalink":"https:\/\/www.facebook.com\/l.marchegiani\/posts\/10202032288159011","privacy":{"value":""},"share_count":"0","source_id":"1540549221","tagged_ids":"","type":"","updated_time":"1381840508","with_tags":""},{"actor_id":"100000752736027","post_id":"1540549221_10202032231277589","comment_info":{"can_comment":"1","comment_count":"0","comment_order":"chronological"},"created_time":"1381840069","is_popular":"","likes":{"href":"https:\/\/www.facebook.com\/browse\/likes\/?id=10202032231277589","count":"0","sample":"","friends":"","user_likes":"0","can_like":"1"},"permalink":"https:\/\/www.facebook.com\/l.marchegiani\/posts\/10202032231277589","privacy":{"value":""},"share_count":"0","source_id":"1540549221","tagged_ids":"","type":"","updated_time":"1381840069","with_tags":""},{"actor_id":"1347549711","post_id":"1540549221_10202031997751751","comment_info":{"can_comment":"1","comment_count":"0","comment_order":"chronological"},"created_time":"1381837856","is_popular":"","likes":{"href":"https:\/\/www.facebook.com\/browse\/likes\/?id=10202031997751751","count":"0","sample":"","friends":"","user_likes":"0","can_like":"1"},"permalink":"https:\/\/www.facebook.com\/l.marchegiani\/posts\/10202031997751751","privacy":{"value":""},"share_count":"0","source_id":"1540549221","tagged_ids":"","type":"","updated_time":"1381837856","with_tags":""},{"actor_id":"1333291077","post_id":"1540549221_10202031886588972","comment_info":{"can_comment":"1","comment_count":"0","comment_order":"chronological"},"created_time":"1381836078","is_popular":"","likes":{"href":"https:\/\/www.facebook.com\/browse\/likes\/?id=10202031886588972","count":"0","sample":"","friends":"","user_likes":"0","can_like":"1"},"permalink":"https:\/\/www.facebook.com\/l.marchegiani\/posts\/10202031886588972","privacy":{"value":""},"share_count":"0","source_id":"1540549221","tagged_ids":"","type":"","updated_time":"1381836078","with_tags":""},{"actor_id":"1558808530","post_id":"1540549221_10202031877948756","comment_info":{"can_comment":"1","comment_count":"0","comment_order":"chronological"},"created_time":"1381835892","is_popular":"","likes":{"href":"https:\/\/www.facebook.com\/browse\/likes\/?id=10202031877948756","count":"0","sample":"","friends":"","user_likes":"0","can_like":"1"},"permalink":"https:\/\/www.facebook.com\/l.marchegiani\/posts\/10202031877948756","privacy":{"value":""},"share_count":"0","source_id":"1540549221","tagged_ids":"","type":"","updated_time":"1381835892","with_tags":""},{"actor_id":"1482416509","post_id":"1540549221_10202031738025258","comment_info":{"can_comment":"1","comment_count":"0","comment_order":"chronological"},"created_time":"1381833171","is_popular":"","likes":{"href":"https:\/\/www.facebook.com\/browse\/likes\/?id=10202031738025258","count":"0","sample":"","friends":"","user_likes":"0","can_like":"1"},"permalink":"https:\/\/www.facebook.com\/l.marchegiani\/posts\/10202031738025258","privacy":{"value":""},"share_count":"0","source_id":"1540549221","tagged_ids":"","type":"","updated_time":"1381833171","with_tags":""},{"actor_id":"1611000839","post_id":"1540549221_10202031713264639","comment_info":{"can_comment":"1","comment_count":"0","comment_order":"chronological"},"created_time":"1381832679","is_popular":"","likes":{"href":"https:\/\/www.facebook.com\/browse\/likes\/?id=10202031713264639","count":"0","sample":"","friends":"","user_likes":"0","can_like":"1"},"permalink":"https:\/\/www.facebook.com\/l.marchegiani\/posts\/10202031713264639","privacy":{"value":""},"share_count":"0","source_id":"1540549221","tagged_ids":"","type":"","updated_time":"1381832679","with_tags":""},{"actor_id":"1036994818","post_id":"1540549221_10202031710304565","comment_info":{"can_comment":"1","comment_count":"0","comment_order":"chronological"},"created_time":"1381832609","is_popular":"","likes":{"href":"https:\/\/www.facebook.com\/browse\/likes\/?id=10202031710304565","count":"0","sample":"","friends":"","user_likes":"0","can_like":"1"},"permalink":"https:\/\/www.facebook.com\/l.marchegiani\/posts\/10202031710304565","privacy":{"value":""},"share_count":"0","source_id":"1540549221","tagged_ids":"","type":"","updated_time":"1381832609","with_tags":""},{"actor_id":"1263456522","post_id":"1540549221_10202031610342066","comment_info":{"can_comment":"1","comment_count":"0","comment_order":"chronological"},"created_time":"1381830151","is_popular":"","likes":{"href":"https:\/\/www.facebook.com\/browse\/likes\/?id=10202031610342066","count":"0","sample":"","friends":"","user_likes":"0","can_like":"1"},"permalink":"https:\/\/www.facebook.com\/l.marchegiani\/posts\/10202031610342066","privacy":{"value":""},"share_count":"0","source_id":"1540549221","tagged_ids":"","type":"","updated_time":"1381830151","with_tags":""},{"actor_id":"1616146457","post_id":"1540549221_10202031582381367","comment_info":{"can_comment":"1","comment_count":"0","comment_order":"chronological"},"created_time":"1381829432","is_popular":"","likes":{"href":"https:\/\/www.facebook.com\/browse\/likes\/?id=10202031582381367","count":"0","sample":"","friends":"","user_likes":"0","can_like":"1"},"permalink":"https:\/\/www.facebook.com\/l.marchegiani\/posts\/10202031582381367","privacy":{"value":""},"share_count":"0","source_id":"1540549221","tagged_ids":"","type":"","updated_time":"1381829432","with_tags":""},{"actor_id":"100000972794900","post_id":"1540549221_10202031521899855","comment_info":{"can_comment":"1","comment_count":"0","comment_order":"chronological"},"created_time":"1381828330","is_popular":"","likes":{"href":"https:\/\/www.facebook.com\/browse\/likes\/?id=10202031521899855","count":"0","sample":"","friends":"","user_likes":"0","can_like":"1"},"permalink":"https:\/\/www.facebook.com\/l.marchegiani\/posts\/10202031521899855","privacy":{"value":""},"share_count":"0","source_id":"1540549221","tagged_ids":"","type":"","updated_time":"1381828330","with_tags":""},{"actor_id":"1411881483","post_id":"1540549221_10202031501059334","comment_info":{"can_comment":"1","comment_count":"0","comment_order":"chronological"},"created_time":"1381827891","is_popular":"","likes":{"href":"https:\/\/www.facebook.com\/browse\/likes\/?id=10202031501059334","count":"0","sample":"","friends":"","user_likes":"0","can_like":"1"},"permalink":"https:\/\/www.facebook.com\/l.marchegiani\/posts\/10202031501059334","privacy":{"value":""},"share_count":"0","source_id":"1540549221","tagged_ids":"","type":"","updated_time":"1381827891","with_tags":""},{"actor_id":"100002951741956","post_id":"1540549221_10202031468978532","comment_info":{"can_comment":"1","comment_count":"0","comment_order":"chronological"},"created_time":"1381827375","is_popular":"","likes":{"href":"https:\/\/www.facebook.com\/browse\/likes\/?id=10202031468978532","count":"0","sample":"","friends":"","user_likes":"0","can_like":"1"},"permalink":"https:\/\/www.facebook.com\/l.marchegiani\/posts\/10202031468978532","privacy":{"value":""},"share_count":"0","source_id":"1540549221","tagged_ids":"","type":"","updated_time":"1381827375","with_tags":""},{"actor_id":"100003303433281","post_id":"1540549221_10202031464618423","comment_info":{"can_comment":"1","comment_count":"0","comment_order":"chronological"},"created_time":"1381827343","is_popular":"","likes":{"href":"https:\/\/www.facebook.com\/browse\/likes\/?id=10202031464618423","count":"0","sample":"","friends":"","user_likes":"0","can_like":"1"},"permalink":"https:\/\/www.facebook.com\/l.marchegiani\/posts\/10202031464618423","privacy":{"value":""},"share_count":"0","source_id":"1540549221","tagged_ids":"","type":"","updated_time":"1381827343","with_tags":""},{"actor_id":"1284045281","post_id":"1540549221_10202031461018333","comment_info":{"can_comment":"1","comment_count":"0","comment_order":"chronological"},"created_time":"1381827247","is_popular":"","likes":{"href":"https:\/\/www.facebook.com\/browse\/likes\/?id=10202031461018333","count":"0","sample":"","friends":"","user_likes":"0","can_like":"1"},"permalink":"https:\/\/www.facebook.com\/l.marchegiani\/posts\/10202031461018333","privacy":{"value":""},"share_count":"0","source_id":"1540549221","tagged_ids":"","type":"","updated_time":"1381827247","with_tags":""},{"actor_id":"100001028749745","post_id":"1540549221_10202031382056359","comment_info":{"can_comment":"1","comment_count":"0","comment_order":"chronological"},"created_time":"1381825566","is_popular":"","likes":{"href":"https:\/\/www.facebook.com\/browse\/likes\/?id=10202031382056359","count":"0","sample":"","friends":"","user_likes":"0","can_like":"1"},"permalink":"https:\/\/www.facebook.com\/l.marchegiani\/posts\/10202031382056359","privacy":{"value":""},"share_count":"0","source_id":"1540549221","tagged_ids":"","type":"","updated_time":"1381825566","with_tags":""},{"actor_id":"1611703159","post_id":"1540549221_10202031358775777","comment_info":{"can_comment":"1","comment_count":"0","comment_order":"chronological"},"created_time":"1381825053","is_popular":"","likes":{"href":"https:\/\/www.facebook.com\/browse\/likes\/?id=10202031358775777","count":"0","sample":"","friends":"","user_likes":"0","can_like":"1"},"permalink":"https:\/\/www.facebook.com\/l.marchegiani\/posts\/10202031358775777","privacy":{"value":""},"share_count":"0","source_id":"1540549221","tagged_ids":"","type":"","updated_time":"1381825053","with_tags":""},{"actor_id":"1391991330","post_id":"1540549221_10202031344975432","comment_info":{"can_comment":"1","comment_count":"0","comment_order":"chronological"},"created_time":"1381824734","is_popular":"","likes":{"href":"https:\/\/www.facebook.com\/browse\/likes\/?id=10202031344975432","count":"0","sample":"","friends":"","user_likes":"0","can_like":"1"},"permalink":"https:\/\/www.facebook.com\/l.marchegiani\/posts\/10202031344975432","privacy":{"value":""},"share_count":"0","source_id":"1540549221","tagged_ids":"","type":"","updated_time":"1381824734","with_tags":""},{"actor_id":"1666005437","post_id":"1540549221_10202031326974982","comment_info":{"can_comment":"1","comment_count":"0","comment_order":"chronological"},"created_time":"1381824349","is_popular":"","likes":{"href":"https:\/\/www.facebook.com\/browse\/likes\/?id=10202031326974982","count":"0","sample":"","friends":"","user_likes":"0","can_like":"1"},"permalink":"https:\/\/www.facebook.com\/l.marchegiani\/posts\/10202031326974982","privacy":{"value":""},"share_count":"0","source_id":"1540549221","tagged_ids":"","type":"","updated_time":"1381824349","with_tags":""},{"actor_id":"100001665558107","post_id":"1540549221_10202031280333816","comment_info":{"can_comment":"1","comment_count":"0","comment_order":"chronological"},"created_time":"1381823128","is_popular":"","likes":{"href":"https:\/\/www.facebook.com\/browse\/likes\/?id=10202031280333816","count":"0","sample":"","friends":"","user_likes":"0","can_like":"1"},"permalink":"https:\/\/www.facebook.com\/l.marchegiani\/posts\/10202031280333816","privacy":{"value":""},"share_count":"0","source_id":"1540549221","tagged_ids":"","type":"","updated_time":"1381823128","with_tags":""},{"actor_id":"1561121527","post_id":"1540549221_10202031233772652","comment_info":{"can_comment":"1","comment_count":"0","comment_order":"chronological"},"created_time":"1381821793","is_popular":"","likes":{"href":"https:\/\/www.facebook.com\/browse\/likes\/?id=10202031233772652","count":"0","sample":"","friends":"","user_likes":"0","can_like":"1"},"permalink":"https:\/\/www.facebook.com\/l.marchegiani\/posts\/10202031233772652","privacy":{"value":""},"share_count":"0","source_id":"1540549221","tagged_ids":["102717363144560"],"type":"","updated_time":"1381821793","with_tags":""},{"actor_id":"1579820634","post_id":"1540549221_10202031221932356","comment_info":{"can_comment":"1","comment_count":"0","comment_order":"chronological"},"created_time":"1381821676","is_popular":"","likes":{"href":"https:\/\/www.facebook.com\/browse\/likes\/?id=10202031221932356","count":"0","sample":"","friends":"","user_likes":"0","can_like":"1"},"permalink":"https:\/\/www.facebook.com\/l.marchegiani\/posts\/10202031221932356","privacy":{"value":""},"share_count":"0","source_id":"1540549221","tagged_ids":"","type":"","updated_time":"1381821676","with_tags":""},{"actor_id":"1662258203","post_id":"1540549221_10202031214532171","comment_info":{"can_comment":"1","comment_count":"0","comment_order":"chronological"},"created_time":"1381821465","is_popular":"","likes":{"href":"https:\/\/www.facebook.com\/browse\/likes\/?id=10202031214532171","count":"0","sample":"","friends":"","user_likes":"0","can_like":"1"},"permalink":"https:\/\/www.facebook.com\/l.marchegiani\/posts\/10202031214532171","privacy":{"value":""},"share_count":"0","source_id":"1540549221","tagged_ids":"","type":"","updated_time":"1381821465","with_tags":""},{"actor_id":"100000015531407","post_id":"1540549221_10202031210132061","comment_info":{"can_comment":"1","comment_count":"0","comment_order":"chronological"},"created_time":"1381821335","is_popular":"","likes":{"href":"https:\/\/www.facebook.com\/browse\/likes\/?id=10202031210132061","count":"0","sample":"","friends":"","user_likes":"0","can_like":"1"},"permalink":"https:\/\/www.facebook.com\/l.marchegiani\/posts\/10202031210132061","privacy":{"value":""},"share_count":"0","source_id":"1540549221","tagged_ids":"","type":"","updated_time":"1381821335","with_tags":""},{"actor_id":"1652567346","post_id":"1540549221_10202031209892055","comment_info":{"can_comment":"1","comment_count":"0","comment_order":"chronological"},"created_time":"1381821331","is_popular":"","likes":{"href":"https:\/\/www.facebook.com\/browse\/likes\/?id=10202031209892055","count":"0","sample":"","friends":"","user_likes":"0","can_like":"1"},"permalink":"https:\/\/www.facebook.com\/l.marchegiani\/posts\/10202031209892055","privacy":{"value":""},"share_count":"0","source_id":"1540549221","tagged_ids":"","type":"","updated_time":"1381821331","with_tags":""},{"actor_id":"1634497079","post_id":"1540549221_10202031196491720","comment_info":{"can_comment":"1","comment_count":"0","comment_order":"chronological"},"created_time":"1381820957","is_popular":"","likes":{"href":"https:\/\/www.facebook.com\/browse\/likes\/?id=10202031196491720","count":"0","sample":"","friends":"","user_likes":"0","can_like":"1"},"permalink":"https:\/\/www.facebook.com\/l.marchegiani\/posts\/10202031196491720","privacy":{"value":""},"share_count":"0","source_id":"1540549221","tagged_ids":"","type":"","updated_time":"1381820957","with_tags":""},{"actor_id":"724633749","post_id":"1540549221_10202031184811428","comment_info":{"can_comment":"1","comment_count":"0","comment_order":"chronological"},"created_time":"1381820572","is_popular":"","likes":{"href":"https:\/\/www.facebook.com\/browse\/likes\/?id=10202031184811428","count":"0","sample":"","friends":"","user_likes":"0","can_like":"1"},"permalink":"https:\/\/www.facebook.com\/l.marchegiani\/posts\/10202031184811428","privacy":{"value":""},"share_count":"0","source_id":"1540549221","tagged_ids":"","type":"","updated_time":"1381820572","with_tags":""},{"actor_id":"100000633560361","post_id":"1540549221_10202031174451169","comment_info":{"can_comment":"1","comment_count":"0","comment_order":"chronological"},"created_time":"1381820295","is_popular":"","likes":{"href":"https:\/\/www.facebook.com\/browse\/likes\/?id=10202031174451169","count":"0","sample":"","friends":"","user_likes":"0","can_like":"1"},"permalink":"https:\/\/www.facebook.com\/l.marchegiani\/posts\/10202031174451169","privacy":{"value":""},"share_count":"0","source_id":"1540549221","tagged_ids":"","type":"","updated_time":"1381820295","with_tags":""},{"actor_id":"100001938157027","post_id":"1540549221_10202031166730976","comment_info":{"can_comment":"1","comment_count":"0","comment_order":"chronological"},"created_time":"1381820013","is_popular":"","likes":{"href":"https:\/\/www.facebook.com\/browse\/likes\/?id=10202031166730976","count":"1","sample":["100001998152117"],"friends":"","user_likes":"0","can_like":"1"},"permalink":"https:\/\/www.facebook.com\/l.marchegiani\/posts\/10202031166730976","privacy":{"value":""},"share_count":"0","source_id":"1540549221","tagged_ids":"","type":"","updated_time":"1381820013","with_tags":""},{"actor_id":"1440574506","post_id":"1540549221_10202031113689650","comment_info":{"can_comment":"1","comment_count":"0","comment_order":"chronological"},"created_time":"1381818667","is_popular":"","likes":{"href":"https:\/\/www.facebook.com\/browse\/likes\/?id=10202031113689650","count":"0","sample":"","friends":"","user_likes":"0","can_like":"1"},"permalink":"https:\/\/www.facebook.com\/l.marchegiani\/posts\/10202031113689650","privacy":{"value":""},"share_count":"0","source_id":"1540549221","tagged_ids":"","type":"","updated_time":"1381818667","with_tags":""},{"actor_id":"1140820753","post_id":"1540549221_10202031020087310","comment_info":{"can_comment":"1","comment_count":"0","comment_order":"chronological"},"created_time":"1381816396","is_popular":"","likes":{"href":"https:\/\/www.facebook.com\/browse\/likes\/?id=10202031020087310","count":"0","sample":"","friends":"","user_likes":"0","can_like":"1"},"permalink":"https:\/\/www.facebook.com\/l.marchegiani\/posts\/10202031020087310","privacy":{"value":""},"share_count":"0","source_id":"1540549221","tagged_ids":"","type":"","updated_time":"1381816396","with_tags":""},{"actor_id":"1583051344","post_id":"1540549221_10202029204641925","comment_info":{"can_comment":"1","comment_count":"0","comment_order":"chronological"},"created_time":"1381794897","is_popular":"","likes":{"href":"https:\/\/www.facebook.com\/browse\/likes\/?id=10202029204641925","count":"0","sample":"","friends":"","user_likes":"0","can_like":"1"},"permalink":"https:\/\/www.facebook.com\/l.marchegiani\/posts\/10202029204641925","privacy":{"value":""},"share_count":"0","source_id":"1540549221","tagged_ids":"","type":"","updated_time":"1381794897","with_tags":""},{"actor_id":"1363682941","post_id":"1540549221_10202029143840405","comment_info":{"can_comment":"1","comment_count":"0","comment_order":"chronological"},"created_time":"1381793780","is_popular":"","likes":{"href":"https:\/\/www.facebook.com\/browse\/likes\/?id=10202029143840405","count":"0","sample":"","friends":"","user_likes":"0","can_like":"1"},"permalink":"https:\/\/www.facebook.com\/l.marchegiani\/posts\/10202029143840405","privacy":{"value":""},"share_count":"0","source_id":"1540549221","tagged_ids":"","type":"","updated_time":"1381793780","with_tags":""},{"actor_id":"1345022304","post_id":"1540549221_10202029126559973","comment_info":{"can_comment":"1","comment_count":"0","comment_order":"chronological"},"created_time":"1381793656","is_popular":"","likes":{"href":"https:\/\/www.facebook.com\/browse\/likes\/?id=10202029126559973","count":"0","sample":"","friends":"","user_likes":"0","can_like":"1"},"permalink":"https:\/\/www.facebook.com\/l.marchegiani\/posts\/10202029126559973","privacy":{"value":""},"share_count":"0","source_id":"1540549221","tagged_ids":"","type":"","updated_time":"1381793656","with_tags":""},{"actor_id":"1278382506","post_id":"1540549221_10202028462383369","comment_info":{"can_comment":"1","comment_count":"0","comment_order":"chronological"},"created_time":"1381788559","is_popular":"","likes":{"href":"https:\/\/www.facebook.com\/browse\/likes\/?id=10202028462383369","count":"0","sample":"","friends":"","user_likes":"0","can_like":"1"},"permalink":"https:\/\/www.facebook.com\/l.marchegiani\/posts\/10202028462383369","privacy":{"value":""},"share_count":"0","source_id":"1540549221","tagged_ids":"","type":"","updated_time":"1381788559","with_tags":""},{"actor_id":"100000015531407","post_id":"1540549221_671665309510647","comment_info":{"can_comment":"1","comment_count":"0","comment_order":"chronological"},"created_time":"1380902737","is_popular":"","likes":{"href":"https:\/\/www.facebook.com\/browse\/likes\/?id=671665309510647","count":"0","sample":"","friends":"","user_likes":"0","can_like":"1"},"permalink":"https:\/\/www.facebook.com\/l.marchegiani\/posts\/671665309510647","privacy":{"value":""},"share_count":"0","source_id":"1540549221","tagged_ids":"","type":"","updated_time":"1380902737","with_tags":""},{"actor_id":"100000015531407","post_id":"1540549221_663638686979976","comment_info":{"can_comment":"1","comment_count":"0","comment_order":"chronological"},"created_time":"1379627204","is_popular":"","likes":{"href":"https:\/\/www.facebook.com\/browse\/likes\/?id=663638686979976","count":"1","sample":"","friends":["1540549221"],"user_likes":"0","can_like":"1"},"permalink":"https:\/\/www.facebook.com\/l.marchegiani\/posts\/663638686979976","privacy":{"value":""},"share_count":"0","source_id":"1540549221","tagged_ids":"","type":"","updated_time":"1379627204","with_tags":""},{"actor_id":"100000015531407","post_id":"1540549221_653151754695336","comment_info":{"can_comment":"1","comment_count":"0","comment_order":"chronological"},"created_time":"1377726843","is_popular":"","likes":{"href":"https:\/\/www.facebook.com\/browse\/likes\/?id=653151754695336","count":"0","sample":"","friends":"","user_likes":"0","can_like":"1"},"permalink":"https:\/\/www.facebook.com\/l.marchegiani\/posts\/653151754695336","privacy":{"value":""},"share_count":"0","source_id":"1540549221","tagged_ids":"","type":"","updated_time":"1377726843","with_tags":""},{"actor_id":"100000015531407","post_id":"1540549221_632302456780266","comment_info":{"can_comment":"1","comment_count":"0","comment_order":"chronological"},"created_time":"1374079708","is_popular":"","likes":{"href":"https:\/\/www.facebook.com\/browse\/likes\/?id=632302456780266","count":"0","sample":"","friends":"","user_likes":"0","can_like":"1"},"permalink":"https:\/\/www.facebook.com\/l.marchegiani\/posts\/632302456780266","privacy":{"value":""},"share_count":"0","source_id":"1540549221","tagged_ids":"","type":"","updated_time":"1374079708","with_tags":""},{"actor_id":"1216442611","post_id":"1540549221_10201121441068403","comment_info":{"can_comment":"1","comment_count":"0","comment_order":"chronological"},"created_time":"1370454617","is_popular":"","likes":{"href":"https:\/\/www.facebook.com\/browse\/likes\/?id=10201121441068403","count":"0","sample":"","friends":"","user_likes":"0","can_like":"1"},"permalink":"https:\/\/www.facebook.com\/l.marchegiani\/posts\/10201121441068403","privacy":{"value":""},"share_count":"0","source_id":"1540549221","tagged_ids":"","type":"237","updated_time":"1370454617","with_tags":""},{"actor_id":"100002440742696","post_id":"1540549221_10201119378696845","comment_info":{"can_comment":"1","comment_count":"0","comment_order":"chronological"},"created_time":"1370428706","is_popular":"","likes":{"href":"https:\/\/www.facebook.com\/browse\/likes\/?id=10201119378696845","count":"0","sample":"","friends":"","user_likes":"0","can_like":"1"},"permalink":"https:\/\/www.facebook.com\/l.marchegiani\/posts\/10201119378696845","privacy":{"value":""},"share_count":"0","source_id":"1540549221","tagged_ids":"","type":"237","updated_time":"1370428706","with_tags":""}]}