[{"actor_id":"1548840395","post_id":"1548840395_10203765082838072","comment_info":{"can_comment":"1","comment_count":"9","comment_order":"chronological"},"created_time":"1397590808","is_popular":"","likes":{"href":"https:\/\/www.facebook.com\/browse\/likes\/?id=10203765082838072","count":"0","sample":"","friends":"","user_likes":"0","can_like":"1"},"permalink":"https:\/\/www.facebook.com\/fra.poco\/posts\/10203765082838072","privacy":{"value":""},"share_count":"0","source_id":"1548840395","tagged_ids":"","type":"80","updated_time":"1397592376","with_tags":""},{"actor_id":"1548840395","post_id":"1548840395_10203352454842630","comment_info":{"can_comment":"1","comment_count":"0","comment_order":"chronological"},"created_time":"1392579274","is_popular":"","likes":{"href":"https:\/\/www.facebook.com\/browse\/likes\/?id=10203352454842630","count":"1","sample":["100001695783549"],"friends":"","user_likes":"0","can_like":"1"},"permalink":"https:\/\/www.facebook.com\/fra.poco\/posts\/10203352454842630","privacy":{"value":""},"share_count":"0","source_id":"1548840395","tagged_ids":"","type":"46","updated_time":"1392579274","with_tags":""},{"actor_id":"1548840395","post_id":"1548840395_10203337771835564","comment_info":{"can_comment":"1","comment_count":"0","comment_order":"chronological"},"created_time":"1392396216","is_popular":"","likes":{"href":"https:\/\/www.facebook.com\/browse\/likes\/?id=10203337771835564","count":"1","sample":["728016174"],"friends":"","user_likes":"0","can_like":"1"},"permalink":"https:\/\/www.facebook.com\/fra.poco\/posts\/10203337771835564","privacy":{"value":""},"share_count":"0","source_id":"1548840395","tagged_ids":"","type":"80","updated_time":"1392396216","with_tags":""},{"actor_id":"1359774302","post_id":"1548840395_10203062954525303","comment_info":{"can_comment":"1","comment_count":"1","comment_order":"chronological"},"created_time":"1389372769","is_popular":"","likes":{"href":"https:\/\/www.facebook.com\/browse\/likes\/?id=10203062954525303","count":"0","sample":"","friends":"","user_likes":"0","can_like":"1"},"permalink":"https:\/\/www.facebook.com\/fra.poco\/posts\/10203062954525303","privacy":{"value":""},"share_count":"0","source_id":"1548840395","tagged_ids":"","type":"","updated_time":"1389372819","with_tags":""},{"actor_id":"100000293335311","post_id":"1548840395_10203057016776863","comment_info":{"can_comment":"1","comment_count":"1","comment_order":"chronological"},"created_time":"1389292078","is_popular":"","likes":{"href":"https:\/\/www.facebook.com\/browse\/likes\/?id=10203057016776863","count":"0","sample":"","friends":"","user_likes":"0","can_like":"1"},"permalink":"https:\/\/www.facebook.com\/fra.poco\/posts\/10203057016776863","privacy":{"value":""},"share_count":"0","source_id":"1548840395","tagged_ids":"","type":"","updated_time":"1389292549","with_tags":""},{"actor_id":"1548840395","post_id":"1548840395_10202280982456490","comment_info":{"can_comment":"1","comment_count":"0","comment_order":"chronological"},"created_time":"1380916805","is_popular":"","likes":{"href":"https:\/\/www.facebook.com\/browse\/likes\/?id=10202280982456490","count":"0","sample":"","friends":"","user_likes":"0","can_like":"1"},"permalink":"https:\/\/www.facebook.com\/fra.poco\/posts\/10202280982456490","privacy":{"value":""},"share_count":"0","source_id":"1548840395","tagged_ids":"","type":"237","updated_time":"1380916805","with_tags":""},{"actor_id":"1360363393","post_id":"1548840395_10202276615547320","comment_info":{"can_comment":"1","comment_count":"2","comment_order":"chronological"},"created_time":"1380874246","is_popular":"","likes":{"href":"https:\/\/www.facebook.com\/browse\/likes\/?id=10202276615547320","count":"1","sample":"","friends":["1548840395"],"user_likes":"0","can_like":"1"},"permalink":"https:\/\/www.facebook.com\/fra.poco\/posts\/10202276615547320","privacy":{"value":""},"share_count":"0","source_id":"1548840395","tagged_ids":"","type":"","updated_time":"1380898053","with_tags":""},{"actor_id":"1449108101","post_id":"1548840395_10202231542220515","comment_info":{"can_comment":"1","comment_count":"1","comment_order":"chronological"},"created_time":"1380301612","is_popular":"","likes":{"href":"https:\/\/www.facebook.com\/browse\/likes\/?id=10202231542220515","count":"1","sample":"","friends":["1548840395"],"user_likes":"0","can_like":"1"},"permalink":"https:\/\/www.facebook.com\/fra.poco\/posts\/10202231542220515","privacy":{"value":""},"share_count":"0","source_id":"1548840395","tagged_ids":"","type":"","updated_time":"1380301645","with_tags":""},{"actor_id":"524972083","post_id":"1548840395_10151554855912084","comment_info":{"can_comment":"1","comment_count":"3","comment_order":"chronological"},"created_time":"1379093680","is_popular":"","likes":{"href":"https:\/\/www.facebook.com\/browse\/likes\/?id=10151554855912084","count":"1","sample":["1597501216"],"friends":"","user_likes":"0","can_like":"1"},"permalink":"https:\/\/www.facebook.com\/fra.poco\/posts\/10151554855912084","privacy":{"value":""},"share_count":"0","source_id":"1548840395","tagged_ids":"","type":"","updated_time":"1379165992","with_tags":""},{"actor_id":"1548840395","post_id":"1548840395_10202077802337114","comment_info":{"can_comment":"1","comment_count":"0","comment_order":"chronological"},"created_time":"1378581993","is_popular":"","likes":{"href":"https:\/\/www.facebook.com\/browse\/likes\/?id=10202077802337114","count":"2","sample":["100002888269091"],"friends":["1745385892"],"user_likes":"0","can_like":"1"},"permalink":"https:\/\/www.facebook.com\/fra.poco\/posts\/10202077802337114","privacy":{"value":""},"share_count":"0","source_id":"1548840395","tagged_ids":"","type":"237","updated_time":"1378581993","with_tags":""},{"actor_id":"836460098","post_id":"1548840395_10202062120105068","comment_info":{"can_comment":"1","comment_count":"8","comment_order":"chronological"},"created_time":"1378389556","is_popular":"","likes":{"href":"https:\/\/www.facebook.com\/browse\/likes\/?id=10202062120105068","count":"0","sample":"","friends":"","user_likes":"0","can_like":"1"},"permalink":"https:\/\/www.facebook.com\/fra.poco\/posts\/10202062120105068","privacy":{"value":""},"share_count":"0","source_id":"1548840395","tagged_ids":"","type":"","updated_time":"1378740334","with_tags":""},{"actor_id":"836460098","post_id":"1548840395_10202042021042604","comment_info":{"can_comment":"1","comment_count":"2","comment_order":"chronological"},"created_time":"1378141832","is_popular":"","likes":{"href":"https:\/\/www.facebook.com\/browse\/likes\/?id=10202042021042604","count":"0","sample":"","friends":"","user_likes":"0","can_like":"1"},"permalink":"https:\/\/www.facebook.com\/fra.poco\/posts\/10202042021042604","privacy":{"value":""},"share_count":"0","source_id":"1548840395","tagged_ids":"","type":"","updated_time":"1378143222","with_tags":""},{"actor_id":"1548840395","post_id":"1548840395_10201838302989780","comment_info":{"can_comment":"1","comment_count":"0","comment_order":"chronological"},"created_time":"1375729556","is_popular":"","likes":{"href":"https:\/\/www.facebook.com\/browse\/likes\/?id=10201838302989780","count":"2","sample":["100002888269091","1264811216"],"friends":"","user_likes":"0","can_like":"1"},"permalink":"https:\/\/www.facebook.com\/fra.poco\/posts\/10201838302989780","privacy":{"value":""},"share_count":"0","source_id":"1548840395","tagged_ids":"","type":"80","updated_time":"1375729556","with_tags":""},{"actor_id":"1548840395","post_id":"1548840395_10201832717930157","comment_info":{"can_comment":"1","comment_count":"0","comment_order":"chronological"},"created_time":"1375653272","is_popular":"","likes":{"href":"https:\/\/www.facebook.com\/browse\/likes\/?id=10201832717930157","count":"1","sample":"","friends":["1745385892"],"user_likes":"0","can_like":"1"},"permalink":"https:\/\/www.facebook.com\/fra.poco\/posts\/10201832717930157","privacy":{"value":""},"share_count":"0","source_id":"1548840395","tagged_ids":"","type":"46","updated_time":"1375653272","with_tags":""},{"actor_id":"1548840395","post_id":"1548840395_10201790803442321","comment_info":{"can_comment":"1","comment_count":"1","comment_order":"chronological"},"created_time":"1375134018","is_popular":"","likes":{"href":"https:\/\/www.facebook.com\/browse\/likes\/?id=10201790803442321","count":"1","sample":"","friends":["1745385892"],"user_likes":"0","can_like":"1"},"permalink":"https:\/\/www.facebook.com\/fra.poco\/posts\/10201790803442321","privacy":{"value":""},"share_count":"0","source_id":"1548840395","tagged_ids":"","type":"237","updated_time":"1375134076","with_tags":""},{"actor_id":"1548840395","post_id":"1548840395_10201713955401168","comment_info":{"can_comment":"1","comment_count":"0","comment_order":"chronological"},"created_time":"1374352294","is_popular":"","likes":{"href":"https:\/\/www.facebook.com\/browse\/likes\/?id=10201713955201163","count":"1","sample":["100002888269091"],"friends":"","user_likes":"0","can_like":"1"},"permalink":"https:\/\/www.facebook.com\/photo.php?fbid=10201713955201163&set=a.2355678301912.135924.1548840395&type=1","privacy":{"value":""},"share_count":"0","source_id":"1548840395","tagged_ids":"","type":"247","updated_time":"1374352294","with_tags":""},{"actor_id":"100002888269091","post_id":"1548840395_10201671377696752","comment_info":{"can_comment":"1","comment_count":"2","comment_order":"chronological"},"created_time":"1373813001","is_popular":"","likes":{"href":"https:\/\/www.facebook.com\/browse\/likes\/?id=10201671377696752","count":"1","sample":"","friends":["1548840395"],"user_likes":"0","can_like":"1"},"permalink":"https:\/\/www.facebook.com\/fra.poco\/posts\/10201671377696752","privacy":{"value":""},"share_count":"0","source_id":"1548840395","tagged_ids":"","type":"","updated_time":"1373819460","with_tags":""},{"actor_id":"1548840395","post_id":"1548840395_10201634580736851","comment_info":{"can_comment":"1","comment_count":"5","comment_order":"chronological"},"created_time":"1373294368","is_popular":"","likes":{"href":"https:\/\/www.facebook.com\/browse\/likes\/?id=10201573106794426","count":"11","sample":["100000806179278","1107215510","1584290596"],"friends":["1548840395"],"user_likes":"0","can_like":"1"},"permalink":"https:\/\/www.facebook.com\/photo.php?fbid=10201573106794426&set=p.10201573106794426&type=1","privacy":{"value":""},"share_count":"0","source_id":"1548840395","tagged_ids":"","type":"65","updated_time":"1373310503","with_tags":""},{"actor_id":"1548840395","post_id":"1548840395_10201605338485813","comment_info":{"can_comment":"1","comment_count":"0","comment_order":"chronological"},"created_time":"1372929616","is_popular":"","likes":{"href":"https:\/\/www.facebook.com\/browse\/likes\/?id=10201605338125804","count":"1","sample":["100004746398647"],"friends":"","user_likes":"0","can_like":"1"},"permalink":"https:\/\/www.facebook.com\/photo.php?fbid=10201605338125804&set=a.2355678301912.135924.1548840395&type=1","privacy":{"value":""},"share_count":"0","source_id":"1548840395","tagged_ids":"","type":"247","updated_time":"1372929616","with_tags":""},{"actor_id":"1548840395","post_id":"1548840395_10201511994952283","comment_info":{"can_comment":"1","comment_count":"0","comment_order":"chronological"},"created_time":"1371927682","is_popular":"","likes":{"href":"https:\/\/www.facebook.com\/browse\/likes\/?id=10201511994952283","count":"0","sample":"","friends":"","user_likes":"0","can_like":"1"},"permalink":"https:\/\/www.facebook.com\/fra.poco\/posts\/10201511994952283","privacy":{"value":""},"share_count":"0","source_id":"1548840395","tagged_ids":"","type":"237","updated_time":"1371927682","with_tags":""},{"actor_id":"1548840395","post_id":"1548840395_10201511990712177","comment_info":{"can_comment":"1","comment_count":"0","comment_order":"chronological"},"created_time":"1371927656","is_popular":"","likes":{"href":"https:\/\/www.facebook.com\/browse\/likes\/?id=10201511990712177","count":"0","sample":"","friends":"","user_likes":"0","can_like":"1"},"permalink":"https:\/\/www.facebook.com\/fra.poco\/posts\/10201511990712177","privacy":{"value":""},"share_count":"0","source_id":"1548840395","tagged_ids":"","type":"46","updated_time":"1371927656","with_tags":""},{"actor_id":"1548840395","post_id":"1548840395_10201504887414599","comment_info":{"can_comment":"1","comment_count":"0","comment_order":"chronological"},"created_time":"1371841999","is_popular":"","likes":{"href":"https:\/\/www.facebook.com\/browse\/likes\/?id=10201504887414599","count":"0","sample":"","friends":"","user_likes":"0","can_like":"1"},"permalink":"https:\/\/www.facebook.com\/fra.poco\/posts\/10201504887414599","privacy":{"value":""},"share_count":"0","source_id":"1548840395","tagged_ids":"","type":"80","updated_time":"1371841999","with_tags":""},{"actor_id":"1548840395","post_id":"1548840395_10201441462069005","comment_info":{"can_comment":"1","comment_count":"0","comment_order":"chronological"},"created_time":"1371137723","is_popular":"","likes":{"href":"https:\/\/www.facebook.com\/browse\/likes\/?id=10201441462069005","count":"0","sample":"","friends":"","user_likes":"0","can_like":"1"},"permalink":"https:\/\/www.facebook.com\/fra.poco\/posts\/10201441462069005","privacy":{"value":""},"share_count":"0","source_id":"1548840395","tagged_ids":"","type":"46","updated_time":"1371137723","with_tags":""},{"actor_id":"1548840395","post_id":"1548840395_10201435711165236","comment_info":{"can_comment":"1","comment_count":"2","comment_order":"chronological"},"created_time":"1371073158","is_popular":"","likes":{"href":"https:\/\/www.facebook.com\/browse\/likes\/?id=10201435711165236","count":"0","sample":"","friends":"","user_likes":"0","can_like":"1"},"permalink":"https:\/\/www.facebook.com\/fra.poco\/posts\/10201435711165236","privacy":{"value":""},"share_count":"0","source_id":"1548840395","tagged_ids":"","type":"80","updated_time":"1371075622","with_tags":""},{"actor_id":"1548840395","post_id":"1548840395_10201435708645173","comment_info":{"can_comment":"1","comment_count":"7","comment_order":"chronological"},"created_time":"1371073134","is_popular":"","likes":{"href":"https:\/\/www.facebook.com\/browse\/likes\/?id=10201435708645173","count":"0","sample":"","friends":"","user_likes":"0","can_like":"1"},"permalink":"https:\/\/www.facebook.com\/fra.poco\/posts\/10201435708645173","privacy":{"value":""},"share_count":"0","source_id":"1548840395","tagged_ids":"","type":"80","updated_time":"1371075607","with_tags":""},{"actor_id":"1548840395","post_id":"1548840395_10201405957421411","comment_info":{"can_comment":"1","comment_count":"0","comment_order":"chronological"},"created_time":"1370699560","is_popular":"","likes":{"href":"https:\/\/www.facebook.com\/browse\/likes\/?id=10201143396977564","count":"0","sample":"","friends":"","user_likes":"0","can_like":"1"},"permalink":"https:\/\/www.facebook.com\/photo.php?fbid=10201143396977564&set=a.3058819720008.151248.1548840395&type=1&relevant_count=1","privacy":{"value":""},"share_count":"0","source_id":"1548840395","tagged_ids":"","type":"","updated_time":"1370699560","with_tags":""},{"actor_id":"1548840395","post_id":"1548840395_10201387921810532","comment_info":{"can_comment":"1","comment_count":"3","comment_order":"chronological"},"created_time":"1370552187","is_popular":"","likes":{"href":"https:\/\/www.facebook.com\/browse\/likes\/?id=10201387921810532","count":"0","sample":"","friends":"","user_likes":"0","can_like":"1"},"permalink":"https:\/\/www.facebook.com\/fra.poco\/posts\/10201387921810532","privacy":{"value":""},"share_count":"0","source_id":"1548840395","tagged_ids":"","type":"237","updated_time":"1370698625","with_tags":""},{"actor_id":"1548840395","post_id":"1548840395_10201352558246465","comment_info":{"can_comment":"1","comment_count":"7","comment_order":"chronological"},"created_time":"1370174007","is_popular":"","likes":{"href":"https:\/\/www.facebook.com\/browse\/likes\/?id=10201352558246465","count":"1","sample":["670589695"],"friends":"","user_likes":"0","can_like":"1"},"permalink":"https:\/\/www.facebook.com\/fra.poco\/posts\/10201352558246465","privacy":{"value":""},"share_count":"0","source_id":"1548840395","tagged_ids":"","type":"46","updated_time":"1370202999","with_tags":""},{"actor_id":"1548840395","post_id":"1548840395_10201327272054326","comment_info":{"can_comment":"1","comment_count":"2","comment_order":"chronological"},"created_time":"1369833873","is_popular":"","likes":{"href":"https:\/\/www.facebook.com\/browse\/likes\/?id=10201327272054326","count":"1","sample":"","friends":["100002888949752"],"user_likes":"0","can_like":"1"},"permalink":"https:\/\/www.facebook.com\/fra.poco\/posts\/10201327272054326","privacy":{"value":""},"share_count":"0","source_id":"1548840395","tagged_ids":"","type":"80","updated_time":"1369837183","with_tags":""},{"actor_id":"1548840395","post_id":"1548840395_10201323352676344","comment_info":{"can_comment":"1","comment_count":"0","comment_order":"chronological"},"created_time":"1369771553","is_popular":"","likes":{"href":"https:\/\/www.facebook.com\/browse\/likes\/?id=10201323352676344","count":"1","sample":["1147790349"],"friends":"","user_likes":"0","can_like":"1"},"permalink":"https:\/\/www.facebook.com\/fra.poco\/posts\/10201323352676344","privacy":{"value":""},"share_count":"0","source_id":"1548840395","tagged_ids":"","type":"80","updated_time":"1369771553","with_tags":""},{"actor_id":"1548840395","post_id":"1548840395_10201316097814977","comment_info":{"can_comment":"1","comment_count":"0","comment_order":"chronological"},"created_time":"1369683730","is_popular":"","likes":{"href":"https:\/\/www.facebook.com\/browse\/likes\/?id=10201316097814977","count":"0","sample":"","friends":"","user_likes":"0","can_like":"1"},"permalink":"https:\/\/www.facebook.com\/fra.poco\/posts\/10201316097814977","privacy":{"value":""},"share_count":"0","source_id":"1548840395","tagged_ids":"","type":"80","updated_time":"1369683730","with_tags":""},{"actor_id":"1548840395","post_id":"1548840395_10201306039843534","comment_info":{"can_comment":"1","comment_count":"2","comment_order":"chronological"},"created_time":"1369567184","is_popular":"","likes":{"href":"https:\/\/www.facebook.com\/browse\/likes\/?id=10201306039843534","count":"1","sample":["100004453991189"],"friends":"","user_likes":"0","can_like":"1"},"permalink":"https:\/\/www.facebook.com\/fra.poco\/posts\/10201306039843534","privacy":{"value":""},"share_count":"0","source_id":"1548840395","tagged_ids":"","type":"46","updated_time":"1369572216","with_tags":""},{"actor_id":"1548840395","post_id":"1548840395_10201297932280850","comment_info":{"can_comment":"1","comment_count":"0","comment_order":"chronological"},"created_time":"1369435742","is_popular":"","likes":{"href":"https:\/\/www.facebook.com\/browse\/likes\/?id=10201297932280850","count":"0","sample":"","friends":"","user_likes":"0","can_like":"1"},"permalink":"https:\/\/www.facebook.com\/fra.poco\/posts\/10201297932280850","privacy":{"value":""},"share_count":"0","source_id":"1548840395","tagged_ids":"","type":"80","updated_time":"1369435742","with_tags":""},{"actor_id":"1548840395","post_id":"1548840395_10201297145141172","comment_info":{"can_comment":"1","comment_count":"0","comment_order":"chronological"},"created_time":"1369425857","is_popular":"","likes":{"href":"https:\/\/www.facebook.com\/browse\/likes\/?id=10201297145141172","count":"1","sample":["1264811216"],"friends":"","user_likes":"0","can_like":"1"},"permalink":"https:\/\/www.facebook.com\/fra.poco\/posts\/10201297145141172","privacy":{"value":""},"share_count":"0","source_id":"1548840395","tagged_ids":"","type":"46","updated_time":"1369425857","with_tags":""},{"actor_id":"1548840395","post_id":"1548840395_10201292061014072","comment_info":{"can_comment":"1","comment_count":"0","comment_order":"chronological"},"created_time":"1369345944","is_popular":"","likes":{"href":"https:\/\/www.facebook.com\/browse\/likes\/?id=10201292061014072","count":"1","sample":["100001695783549"],"friends":"","user_likes":"0","can_like":"1"},"permalink":"https:\/\/www.facebook.com\/fra.poco\/posts\/10201292061014072","privacy":{"value":""},"share_count":"0","source_id":"1548840395","tagged_ids":"","type":"46","updated_time":"1369345944","with_tags":""},{"actor_id":"524972083","post_id":"1548840395_10151370124097084","comment_info":{"can_comment":"1","comment_count":"2","comment_order":"chronological"},"created_time":"1369331745","is_popular":"","likes":{"href":"https:\/\/www.facebook.com\/browse\/likes\/?id=10151370124097084","count":"0","sample":"","friends":"","user_likes":"0","can_like":"1"},"permalink":"https:\/\/www.facebook.com\/fra.poco\/posts\/10151370124097084","privacy":{"value":""},"share_count":"0","source_id":"1548840395","tagged_ids":"","type":"","updated_time":"1369342402","with_tags":""},{"actor_id":"1548840395","post_id":"1548840395_10201289648673765","comment_info":{"can_comment":"1","comment_count":"0","comment_order":"chronological"},"created_time":"1369316446","is_popular":"","likes":{"href":"https:\/\/www.facebook.com\/browse\/likes\/?id=10201289647233729","count":"0","sample":"","friends":"","user_likes":"0","can_like":"1"},"permalink":"https:\/\/www.facebook.com\/photo.php?fbid=10201289647233729&set=a.3058819720008.151248.1548840395&type=1&relevant_count=1","privacy":{"value":""},"share_count":"0","source_id":"1548840395","tagged_ids":"","type":"","updated_time":"1369316446","with_tags":""},{"actor_id":"1548840395","post_id":"1548840395_10201286633358384","comment_info":{"can_comment":"1","comment_count":"0","comment_order":"chronological"},"created_time":"1369259636","is_popular":"","likes":{"href":"https:\/\/www.facebook.com\/browse\/likes\/?id=10201286633358384","count":"0","sample":"","friends":"","user_likes":"0","can_like":"1"},"permalink":"https:\/\/www.facebook.com\/fra.poco\/posts\/10201286633358384","privacy":{"value":""},"share_count":"0","source_id":"1548840395","tagged_ids":"","type":"80","updated_time":"1369259636","with_tags":""},{"actor_id":"1548840395","post_id":"1548840395_10201264621328097","comment_info":{"can_comment":"1","comment_count":"0","comment_order":"chronological"},"created_time":"1368995869","is_popular":"","likes":{"href":"https:\/\/www.facebook.com\/browse\/likes\/?id=10201264621328097","count":"1","sample":"","friends":["1745385892"],"user_likes":"0","can_like":"1"},"permalink":"https:\/\/www.facebook.com\/fra.poco\/posts\/10201264621328097","privacy":{"value":""},"share_count":"0","source_id":"1548840395","tagged_ids":"","type":"46","updated_time":"1368995869","with_tags":""},{"actor_id":"1548840395","post_id":"1548840395_10201159802347688","comment_info":{"can_comment":"1","comment_count":"2","comment_order":"chronological"},"created_time":"1367673609","is_popular":"","likes":{"href":"https:\/\/www.facebook.com\/browse\/likes\/?id=10201159802347688","count":"0","sample":"","friends":"","user_likes":"0","can_like":"1"},"permalink":"https:\/\/www.facebook.com\/fra.poco\/posts\/10201159802347688","privacy":{"value":""},"share_count":"0","source_id":"1548840395","tagged_ids":["100003251063687","1632830282"],"type":"46","updated_time":"1367674034","with_tags":""},{"actor_id":"1548840395","post_id":"1548840395_10201151122890707","comment_info":{"can_comment":"1","comment_count":"0","comment_order":"chronological"},"created_time":"1367529017","is_popular":"","likes":{"href":"https:\/\/www.facebook.com\/browse\/likes\/?id=10201151122890707","count":"1","sample":["100003348410937"],"friends":"","user_likes":"0","can_like":"1"},"permalink":"https:\/\/www.facebook.com\/fra.poco\/posts\/10201151122890707","privacy":{"value":""},"share_count":"0","source_id":"1548840395","tagged_ids":"","type":"46","updated_time":"1367529017","with_tags":""},{"actor_id":"1548840395","post_id":"1548840395_10201143397097567","comment_info":{"can_comment":"1","comment_count":"0","comment_order":"chronological"},"created_time":"1367425078","is_popular":"","likes":{"href":"https:\/\/www.facebook.com\/browse\/likes\/?id=10201143396977564","count":"0","sample":"","friends":"","user_likes":"0","can_like":"1"},"permalink":"https:\/\/www.facebook.com\/photo.php?fbid=10201143396977564&set=a.3058819720008.151248.1548840395&type=1&relevant_count=1","privacy":{"value":""},"share_count":"0","source_id":"1548840395","tagged_ids":"","type":"","updated_time":"1367425078","with_tags":""},{"actor_id":"1645262094","post_id":"1548840395_185394628275149","comment_info":{"can_comment":"1","comment_count":"2","comment_order":"chronological"},"created_time":"1365674891","is_popular":"","likes":{"href":"https:\/\/www.facebook.com\/browse\/likes\/?id=185394628275149","count":"0","sample":"","friends":"","user_likes":"0","can_like":"1"},"permalink":"https:\/\/www.facebook.com\/fra.poco\/posts\/185394628275149","privacy":{"value":""},"share_count":"0","source_id":"1548840395","tagged_ids":"","type":"","updated_time":"1365689032","with_tags":""},{"actor_id":"1548840395","post_id":"1548840395_449381581810233","comment_info":{"can_comment":"1","comment_count":"20","comment_order":"chronological"},"created_time":"1365427223","is_popular":"","likes":{"href":"https:\/\/www.facebook.com\/browse\/likes\/?id=449381581810233","count":"0","sample":"","friends":"","user_likes":"0","can_like":"1"},"permalink":"https:\/\/www.facebook.com\/fra.poco\/posts\/449381581810233","privacy":{"value":""},"share_count":"0","source_id":"1548840395","tagged_ids":"","type":"80","updated_time":"1365431926","with_tags":""},{"actor_id":"1548840395","post_id":"1548840395_517802431599585","comment_info":{"can_comment":"1","comment_count":"0","comment_order":"chronological"},"created_time":"1365191619","is_popular":"","likes":{"href":"https:\/\/www.facebook.com\/browse\/likes\/?id=517802431599585","count":"0","sample":"","friends":"","user_likes":"0","can_like":"1"},"permalink":"https:\/\/www.facebook.com\/fra.poco\/posts\/517802431599585","privacy":{"value":""},"share_count":"0","source_id":"1548840395","tagged_ids":"","type":"80","updated_time":"1365191619","with_tags":""},{"actor_id":"1548840395","post_id":"1548840395_487192284662863","comment_info":{"can_comment":"1","comment_count":"0","comment_order":"chronological"},"created_time":"1365188809","is_popular":"","likes":{"href":"https:\/\/www.facebook.com\/browse\/likes\/?id=487192284662863","count":"0","sample":"","friends":"","user_likes":"0","can_like":"1"},"permalink":"https:\/\/www.facebook.com\/fra.poco\/posts\/487192284662863","privacy":{"value":""},"share_count":"0","source_id":"1548840395","tagged_ids":"","type":"80","updated_time":"1365188809","with_tags":""},{"actor_id":"524972083","post_id":"1548840395_132690296918261","comment_info":{"can_comment":"1","comment_count":"3","comment_order":"chronological"},"created_time":"1365181580","is_popular":"","likes":{"href":"https:\/\/www.facebook.com\/browse\/likes\/?id=132690296918261","count":"0","sample":"","friends":"","user_likes":"0","can_like":"1"},"permalink":"https:\/\/www.facebook.com\/fra.poco\/posts\/132690296918261","privacy":{"value":""},"share_count":"0","source_id":"1548840395","tagged_ids":"","type":"","updated_time":"1365187206","with_tags":""},{"actor_id":"1548840395","post_id":"1548840395_10200960557686696","comment_info":{"can_comment":"1","comment_count":"0","comment_order":"chronological"},"created_time":"1364730116","is_popular":"","likes":{"href":"https:\/\/www.facebook.com\/browse\/likes\/?id=10200960557686696","count":"0","sample":"","friends":"","user_likes":"0","can_like":"1"},"permalink":"https:\/\/www.facebook.com\/fra.poco\/posts\/10200960557686696","privacy":{"value":""},"share_count":"0","source_id":"1548840395","tagged_ids":"","type":"46","updated_time":"1364730116","with_tags":""},{"actor_id":"1548840395","post_id":"1548840395_10200956264979381","comment_info":{"can_comment":"1","comment_count":"4","comment_order":"chronological"},"created_time":"1364673709","is_popular":"","likes":{"href":"https:\/\/www.facebook.com\/browse\/likes\/?id=10200956264979381","count":"1","sample":["100001695783549"],"friends":"","user_likes":"0","can_like":"1"},"permalink":"https:\/\/www.facebook.com\/fra.poco\/posts\/10200956264979381","privacy":{"value":""},"share_count":"0","source_id":"1548840395","tagged_ids":"","type":"46","updated_time":"1364729794","with_tags":""},{"actor_id":"1548840395","post_id":"1548840395_10200918108225486","comment_info":{"can_comment":"1","comment_count":"2","comment_order":"chronological"},"created_time":"1364063401","is_popular":"","likes":{"href":"https:\/\/www.facebook.com\/browse\/likes\/?id=10200918108225486","count":"0","sample":"","friends":"","user_likes":"0","can_like":"1"},"permalink":"https:\/\/www.facebook.com\/fra.poco\/posts\/10200918108225486","privacy":{"value":""},"share_count":"0","source_id":"1548840395","tagged_ids":"","type":"46","updated_time":"1364673805","with_tags":""},{"actor_id":"1548840395","post_id":"1548840395_550471984987332","comment_info":{"can_comment":"1","comment_count":"0","comment_order":"chronological"},"created_time":"1363526699","is_popular":"","likes":{"href":"https:\/\/www.facebook.com\/browse\/likes\/?id=550471984987332","count":"0","sample":"","friends":"","user_likes":"0","can_like":"1"},"permalink":"https:\/\/www.facebook.com\/fra.poco\/posts\/550471984987332","privacy":{"value":""},"share_count":"0","source_id":"1548840395","tagged_ids":"","type":"80","updated_time":"1363526699","with_tags":""},{"actor_id":"1548840395","post_id":"1548840395_10200872298720277","comment_info":{"can_comment":"1","comment_count":"0","comment_order":"chronological"},"created_time":"1363384706","is_popular":"","likes":{"href":"https:\/\/www.facebook.com\/browse\/likes\/?id=10200872298720277","count":"2","sample":["100004746398647","524972083"],"friends":"","user_likes":"0","can_like":"1"},"permalink":"https:\/\/www.facebook.com\/fra.poco\/posts\/10200872298720277","privacy":{"value":""},"share_count":"0","source_id":"1548840395","tagged_ids":"","type":"46","updated_time":"1363384706","with_tags":""},{"actor_id":"1548840395","post_id":"1548840395_10200857442988893","comment_info":{"can_comment":"1","comment_count":"0","comment_order":"chronological"},"created_time":"1363207416","is_popular":"","likes":{"href":"https:\/\/www.facebook.com\/browse\/likes\/?id=10200857442988893","count":"0","sample":"","friends":"","user_likes":"0","can_like":"1"},"permalink":"https:\/\/www.facebook.com\/fra.poco\/posts\/10200857442988893","privacy":{"value":""},"share_count":"0","source_id":"1548840395","tagged_ids":"","type":"46","updated_time":"1363207416","with_tags":""},{"actor_id":"1548840395","post_id":"1548840395_148693605296665","comment_info":{"can_comment":"1","comment_count":"0","comment_order":"chronological"},"created_time":"1362775346","is_popular":"","likes":{"href":"https:\/\/www.facebook.com\/browse\/likes\/?id=148693605296665","count":"1","sample":["524972083"],"friends":"","user_likes":"0","can_like":"1"},"permalink":"https:\/\/www.facebook.com\/fra.poco\/posts\/148693605296665","privacy":{"value":""},"share_count":"0","source_id":"1548840395","tagged_ids":"","type":"80","updated_time":"1362775346","with_tags":""},{"actor_id":"1548840395","post_id":"1548840395_10200808885414984","comment_info":{"can_comment":"1","comment_count":"0","comment_order":"chronological"},"created_time":"1362610389","is_popular":"","likes":{"href":"https:\/\/www.facebook.com\/browse\/likes\/?id=10200808885414984","count":"0","sample":"","friends":"","user_likes":"0","can_like":"1"},"permalink":"https:\/\/www.facebook.com\/fra.poco\/posts\/10200808885414984","privacy":{"value":""},"share_count":"0","source_id":"1548840395","tagged_ids":"","type":"46","updated_time":"1362610389","with_tags":""},{"actor_id":"1548840395","post_id":"1548840395_10200780834273723","comment_info":{"can_comment":"1","comment_count":"0","comment_order":"chronological"},"created_time":"1362432396","is_popular":"","likes":{"href":"https:\/\/www.facebook.com\/browse\/likes\/?id=10200780834273723","count":"1","sample":["524972083"],"friends":"","user_likes":"0","can_like":"1"},"permalink":"https:\/\/www.facebook.com\/fra.poco\/posts\/10200780834273723","privacy":{"value":""},"share_count":"0","source_id":"1548840395","tagged_ids":"","type":"46","updated_time":"1362432396","with_tags":""},{"actor_id":"1548840395","post_id":"1548840395_10200778651699160","comment_info":{"can_comment":"1","comment_count":"0","comment_order":"chronological"},"created_time":"1362415764","is_popular":"","likes":{"href":"https:\/\/www.facebook.com\/browse\/likes\/?id=10200778651699160","count":"0","sample":"","friends":"","user_likes":"0","can_like":"1"},"permalink":"https:\/\/www.facebook.com\/fra.poco\/posts\/10200778651699160","privacy":{"value":""},"share_count":"0","source_id":"1548840395","tagged_ids":"","type":"46","updated_time":"1362415764","with_tags":""},{"actor_id":"1548840395","post_id":"1548840395_10200772018613337","comment_info":{"can_comment":"1","comment_count":"0","comment_order":"chronological"},"created_time":"1362349872","is_popular":"","likes":{"href":"https:\/\/www.facebook.com\/browse\/likes\/?id=10200772018613337","count":"2","sample":["100004746398647","1621383458"],"friends":"","user_likes":"0","can_like":"1"},"permalink":"https:\/\/www.facebook.com\/fra.poco\/posts\/10200772018613337","privacy":{"value":""},"share_count":"0","source_id":"1548840395","tagged_ids":"","type":"46","updated_time":"1362349872","with_tags":""},{"actor_id":"1548840395","post_id":"1548840395_10200769200742892","comment_info":{"can_comment":"1","comment_count":"0","comment_order":"chronological"},"created_time":"1362330241","is_popular":"","likes":{"href":"https:\/\/www.facebook.com\/browse\/likes\/?id=10200769200742892","count":"1","sample":["1437950283"],"friends":"","user_likes":"0","can_like":"1"},"permalink":"https:\/\/www.facebook.com\/fra.poco\/posts\/10200769200742892","privacy":{"value":""},"share_count":"0","source_id":"1548840395","tagged_ids":"","type":"46","updated_time":"1362330241","with_tags":""},{"actor_id":"1548840395","post_id":"1548840395_10200700204898039","comment_info":{"can_comment":"1","comment_count":"0","comment_order":"chronological"},"created_time":"1361400849","is_popular":"","likes":{"href":"https:\/\/www.facebook.com\/browse\/likes\/?id=10200700204898039","count":"1","sample":["100004746398647"],"friends":"","user_likes":"0","can_like":"1"},"permalink":"https:\/\/www.facebook.com\/fra.poco\/posts\/10200700204898039","privacy":{"value":""},"share_count":"0","source_id":"1548840395","tagged_ids":"","type":"46","updated_time":"1361400849","with_tags":""},{"actor_id":"1548840395","post_id":"1548840395_10200697979322401","comment_info":{"can_comment":"1","comment_count":"0","comment_order":"chronological"},"created_time":"1361374932","is_popular":"","likes":{"href":"https:\/\/www.facebook.com\/browse\/likes\/?id=10200697979322401","count":"0","sample":"","friends":"","user_likes":"0","can_like":"1"},"permalink":"https:\/\/www.facebook.com\/fra.poco\/posts\/10200697979322401","privacy":{"value":""},"share_count":"0","source_id":"1548840395","tagged_ids":"","type":"46","updated_time":"1361374932","with_tags":""},{"actor_id":"1548840395","post_id":"1548840395_10200676501025457","comment_info":{"can_comment":"1","comment_count":"4","comment_order":"chronological"},"created_time":"1361061851","is_popular":"","likes":{"href":"https:\/\/www.facebook.com\/browse\/likes\/?id=10200676501025457","count":"2","sample":["100000281172494","100001695783549"],"friends":"","user_likes":"0","can_like":"1"},"permalink":"https:\/\/www.facebook.com\/fra.poco\/posts\/10200676501025457","privacy":{"value":""},"share_count":"0","source_id":"1548840395","tagged_ids":"","type":"46","updated_time":"1361062559","with_tags":""},{"actor_id":"1548840395","post_id":"1548840395_10200672740731452","comment_info":{"can_comment":"1","comment_count":"0","comment_order":"chronological"},"created_time":"1361021973","is_popular":"","likes":{"href":"https:\/\/www.facebook.com\/browse\/likes\/?id=10200672740731452","count":"4","sample":["100004746398647","100003251063687","524972083"],"friends":["1477755458"],"user_likes":"0","can_like":"1"},"permalink":"https:\/\/www.facebook.com\/fra.poco\/posts\/10200672740731452","privacy":{"value":""},"share_count":"0","source_id":"1548840395","tagged_ids":"","type":"46","updated_time":"1361021973","with_tags":""},{"actor_id":"1548840395","post_id":"1548840395_264730480325988","comment_info":{"can_comment":"1","comment_count":"1","comment_order":"chronological"},"created_time":"1360707061","is_popular":"","likes":{"href":"https:\/\/www.facebook.com\/browse\/likes\/?id=264730480325988","count":"0","sample":"","friends":"","user_likes":"0","can_like":"1"},"permalink":"https:\/\/www.facebook.com\/fra.poco\/posts\/264730480325988","privacy":{"value":""},"share_count":"0","source_id":"1548840395","tagged_ids":"","type":"80","updated_time":"1360848963","with_tags":""},{"actor_id":"1548840395","post_id":"1548840395_506832486054919","comment_info":{"can_comment":"1","comment_count":"0","comment_order":"chronological"},"created_time":"1360339585","is_popular":"","likes":{"href":"https:\/\/www.facebook.com\/browse\/likes\/?id=506832486054919","count":"0","sample":"","friends":"","user_likes":"0","can_like":"1"},"permalink":"https:\/\/www.facebook.com\/fra.poco\/posts\/506832486054919","privacy":{"value":""},"share_count":"0","source_id":"1548840395","tagged_ids":"","type":"80","updated_time":"1360339585","with_tags":""},{"actor_id":"1548840395","post_id":"1548840395_10200611206193127","comment_info":{"can_comment":"1","comment_count":"5","comment_order":"chronological"},"created_time":"1360334347","is_popular":"","likes":{"href":"https:\/\/www.facebook.com\/browse\/likes\/?id=10200611206193127","count":"2","sample":["524972083"],"friends":["1745385892"],"user_likes":"0","can_like":"1"},"permalink":"https:\/\/www.facebook.com\/fra.poco\/posts\/10200611206193127","privacy":{"value":""},"share_count":"0","source_id":"1548840395","tagged_ids":"","type":"46","updated_time":"1360335657","with_tags":""},{"actor_id":"1548840395","post_id":"1548840395_125527740956656","comment_info":{"can_comment":"1","comment_count":"0","comment_order":"chronological"},"created_time":"1360167237","is_popular":"","likes":{"href":"https:\/\/www.facebook.com\/browse\/likes\/?id=125527740956656","count":"0","sample":"","friends":"","user_likes":"0","can_like":"1"},"permalink":"https:\/\/www.facebook.com\/fra.poco\/posts\/125527740956656","privacy":{"value":""},"share_count":"0","source_id":"1548840395","tagged_ids":"","type":"80","updated_time":"1360167237","with_tags":""},{"actor_id":"524972083","post_id":"1548840395_10200579072949816","comment_info":{"can_comment":"1","comment_count":"1","comment_order":"chronological"},"created_time":"1360012162","is_popular":"","likes":{"href":"https:\/\/www.facebook.com\/browse\/likes\/?id=10200579072949816","count":"0","sample":"","friends":"","user_likes":"0","can_like":"1"},"permalink":"https:\/\/www.facebook.com\/fra.poco\/posts\/10200579072949816","privacy":{"value":""},"share_count":"0","source_id":"1548840395","tagged_ids":"","type":"","updated_time":"1360012492","with_tags":""},{"actor_id":"1548840395","post_id":"1548840395_502438926474867","comment_info":{"can_comment":"1","comment_count":"0","comment_order":"chronological"},"created_time":"1359906046","is_popular":"","likes":{"href":"https:\/\/www.facebook.com\/browse\/likes\/?id=502438926474867","count":"0","sample":"","friends":"","user_likes":"0","can_like":"1"},"permalink":"https:\/\/www.facebook.com\/fra.poco\/posts\/502438926474867","privacy":{"value":""},"share_count":"0","source_id":"1548840395","tagged_ids":"","type":"80","updated_time":"1359906046","with_tags":""},{"actor_id":"1548840395","post_id":"1548840395_10200499421478579","comment_info":{"can_comment":"1","comment_count":"4","comment_order":"chronological"},"created_time":"1359840803","is_popular":"","likes":{"href":"https:\/\/www.facebook.com\/browse\/likes\/?id=10200499421478579","count":"2","sample":["1380400784","524972083"],"friends":"","user_likes":"0","can_like":"1"},"permalink":"https:\/\/www.facebook.com\/fra.poco\/posts\/10200499421478579","privacy":{"value":""},"share_count":"0","source_id":"1548840395","tagged_ids":"","type":"46","updated_time":"1359848525","with_tags":""},{"actor_id":"1548840395","post_id":"1548840395_139366232892304","comment_info":{"can_comment":"1","comment_count":"0","comment_order":"chronological"},"created_time":"1359801166","is_popular":"","likes":{"href":"https:\/\/www.facebook.com\/browse\/likes\/?id=139366232892304","count":"2","sample":["100004746398647","100002029008286"],"friends":"","user_likes":"0","can_like":"1"},"permalink":"https:\/\/www.facebook.com\/fra.poco\/posts\/139366232892304","privacy":{"value":""},"share_count":"0","source_id":"1548840395","tagged_ids":"","type":"80","updated_time":"1359801166","with_tags":""},{"actor_id":"1548840395","post_id":"1548840395_10200413314485958","comment_info":{"can_comment":"1","comment_count":"0","comment_order":"chronological"},"created_time":"1358717540","is_popular":"","likes":{"href":"https:\/\/www.facebook.com\/browse\/likes\/?id=10200413314485958","count":"1","sample":["524972083"],"friends":"","user_likes":"0","can_like":"1"},"permalink":"https:\/\/www.facebook.com\/fra.poco\/posts\/10200413314485958","privacy":{"value":""},"share_count":"0","source_id":"1548840395","tagged_ids":"","type":"46","updated_time":"1358717540","with_tags":""},{"actor_id":"1548840395","post_id":"1548840395_320970284669637","comment_info":{"can_comment":"1","comment_count":"0","comment_order":"chronological"},"created_time":"1358522013","is_popular":"","likes":{"href":"https:\/\/www.facebook.com\/browse\/likes\/?id=320970284669637","count":"0","sample":"","friends":"","user_likes":"0","can_like":"1"},"permalink":"https:\/\/www.facebook.com\/fra.poco\/posts\/320970284669637","privacy":{"value":""},"share_count":"0","source_id":"1548840395","tagged_ids":"","type":"80","updated_time":"1358522013","with_tags":""},{"actor_id":"1548840395","post_id":"1548840395_318666601586442","comment_info":{"can_comment":"1","comment_count":"0","comment_order":"chronological"},"created_time":"1358032840","is_popular":"","likes":{"href":"https:\/\/www.facebook.com\/browse\/likes\/?id=318666601586442","count":"0","sample":"","friends":"","user_likes":"0","can_like":"1"},"permalink":"https:\/\/www.facebook.com\/fra.poco\/posts\/318666601586442","privacy":{"value":""},"share_count":"0","source_id":"1548840395","tagged_ids":"","type":"80","updated_time":"1358032840","with_tags":""},{"actor_id":"1548840395","post_id":"1548840395_10200363620043628","comment_info":{"can_comment":"1","comment_count":"23","comment_order":"chronological"},"created_time":"1358031467","is_popular":"","likes":{"href":"https:\/\/www.facebook.com\/browse\/likes\/?id=10200363620043628","count":"0","sample":"","friends":"","user_likes":"0","can_like":"1"},"permalink":"https:\/\/www.facebook.com\/fra.poco\/posts\/10200363620043628","privacy":{"value":""},"share_count":"0","source_id":"1548840395","tagged_ids":"","type":"46","updated_time":"1358032013","with_tags":""},{"actor_id":"1548840395","post_id":"1548840395_409578945791793","comment_info":{"can_comment":"1","comment_count":"0","comment_order":"chronological"},"created_time":"1357847794","is_popular":"","likes":{"href":"https:\/\/www.facebook.com\/browse\/likes\/?id=409578945791793","count":"0","sample":"","friends":"","user_likes":"0","can_like":"1"},"permalink":"https:\/\/www.facebook.com\/fra.poco\/posts\/409578945791793","privacy":{"value":""},"share_count":"0","source_id":"1548840395","tagged_ids":"","type":"80","updated_time":"1357847794","with_tags":""},{"actor_id":"1548840395","post_id":"1548840395_133993433426213","comment_info":{"can_comment":"1","comment_count":"0","comment_order":"chronological"},"created_time":"1357251132","is_popular":"","likes":{"href":"https:\/\/www.facebook.com\/browse\/likes\/?id=133993433426213","count":"1","sample":["697318472"],"friends":"","user_likes":"0","can_like":"1"},"permalink":"https:\/\/www.facebook.com\/fra.poco\/posts\/133993433426213","privacy":{"value":""},"share_count":"0","source_id":"1548840395","tagged_ids":"","type":"80","updated_time":"1357251132","with_tags":""},{"actor_id":"1548840395","post_id":"1548840395_10200254992688012","comment_info":{"can_comment":"1","comment_count":"2","comment_order":"chronological"},"created_time":"1356520291","is_popular":"","likes":{"href":"https:\/\/www.facebook.com\/browse\/likes\/?id=10200254992688012","count":"1","sample":["100003348410937"],"friends":"","user_likes":"0","can_like":"1"},"permalink":"https:\/\/www.facebook.com\/fra.poco\/posts\/10200254992688012","privacy":{"value":""},"share_count":"0","source_id":"1548840395","tagged_ids":"","type":"46","updated_time":"1356520711","with_tags":""},{"actor_id":"1548840395","post_id":"1548840395_467313746637401","comment_info":{"can_comment":"1","comment_count":"0","comment_order":"chronological"},"created_time":"1356361301","is_popular":"","likes":{"href":"https:\/\/www.facebook.com\/browse\/likes\/?id=467313746637401","count":"0","sample":"","friends":"","user_likes":"0","can_like":"1"},"permalink":"https:\/\/www.facebook.com\/fra.poco\/posts\/467313746637401","privacy":{"value":""},"share_count":"0","source_id":"1548840395","tagged_ids":"","type":"80","updated_time":"1356361301","with_tags":""},{"actor_id":"1548840395","post_id":"1548840395_10200222431193995","comment_info":{"can_comment":"1","comment_count":"0","comment_order":"chronological"},"created_time":"1356042174","is_popular":"","likes":{"href":"https:\/\/www.facebook.com\/browse\/likes\/?id=10200222431193995","count":"1","sample":["100003348410937"],"friends":"","user_likes":"0","can_like":"1"},"permalink":"https:\/\/www.facebook.com\/fra.poco\/posts\/10200222431193995","privacy":{"value":""},"share_count":"0","source_id":"1548840395","tagged_ids":"","type":"46","updated_time":"1356042174","with_tags":""},{"actor_id":"1548840395","post_id":"1548840395_574420572585029","comment_info":{"can_comment":"1","comment_count":"0","comment_order":"chronological"},"created_time":"1355782843","is_popular":"","likes":{"href":"https:\/\/www.facebook.com\/browse\/likes\/?id=574420572585029","count":"0","sample":"","friends":"","user_likes":"0","can_like":"1"},"permalink":"https:\/\/www.facebook.com\/fra.poco\/posts\/574420572585029","privacy":{"value":""},"share_count":"0","source_id":"1548840395","tagged_ids":"","type":"80","updated_time":"1355782843","with_tags":""},{"actor_id":"1548840395","post_id":"1548840395_10200205777177655","comment_info":{"can_comment":"1","comment_count":"1","comment_order":"chronological"},"created_time":"1355777192","is_popular":"","likes":{"href":"https:\/\/www.facebook.com\/browse\/likes\/?id=10200205777177655","count":"2","sample":["100001695783549","100003348410937"],"friends":"","user_likes":"0","can_like":"1"},"permalink":"https:\/\/www.facebook.com\/fra.poco\/posts\/10200205777177655","privacy":{"value":""},"share_count":"0","source_id":"1548840395","tagged_ids":"","type":"46","updated_time":"1355778002","with_tags":""},{"actor_id":"1548840395","post_id":"1548840395_145500655598869","comment_info":{"can_comment":"1","comment_count":"0","comment_order":"chronological"},"created_time":"1355753557","is_popular":"","likes":{"href":"https:\/\/www.facebook.com\/browse\/likes\/?id=145500655598869","count":"0","sample":"","friends":"","user_likes":"0","can_like":"1"},"permalink":"https:\/\/www.facebook.com\/fra.poco\/posts\/145500655598869","privacy":{"value":""},"share_count":"0","source_id":"1548840395","tagged_ids":"","type":"80","updated_time":"1355753557","with_tags":""},{"actor_id":"1548840395","post_id":"1548840395_10200199999713222","comment_info":{"can_comment":"1","comment_count":"0","comment_order":"chronological"},"created_time":"1355694477","is_popular":"","likes":{"href":"https:\/\/www.facebook.com\/browse\/likes\/?id=10200199999713222","count":"0","sample":"","friends":"","user_likes":"0","can_like":"1"},"permalink":"https:\/\/www.facebook.com\/fra.poco\/posts\/10200199999713222","privacy":{"value":""},"share_count":"0","source_id":"1548840395","tagged_ids":"","type":"46","updated_time":"1355694477","with_tags":""},{"actor_id":"1548840395","post_id":"1548840395_10200183367377424","comment_info":{"can_comment":"1","comment_count":"0","comment_order":"chronological"},"created_time":"1355430975","is_popular":"","likes":{"href":"https:\/\/www.facebook.com\/browse\/likes\/?id=10200183367377424","count":"0","sample":"","friends":"","user_likes":"0","can_like":"1"},"permalink":"https:\/\/www.facebook.com\/fra.poco\/posts\/10200183367377424","privacy":{"value":""},"share_count":"0","source_id":"1548840395","tagged_ids":"","type":"46","updated_time":"1355430975","with_tags":""},{"actor_id":"1548840395","post_id":"1548840395_10200174292310553","comment_info":{"can_comment":"1","comment_count":"0","comment_order":"chronological"},"created_time":"1355267419","is_popular":"","likes":{"href":"https:\/\/www.facebook.com\/browse\/likes\/?id=10200174292310553","count":"0","sample":"","friends":"","user_likes":"0","can_like":"1"},"permalink":"https:\/\/www.facebook.com\/fra.poco\/posts\/10200174292310553","privacy":{"value":""},"share_count":"0","source_id":"1548840395","tagged_ids":"","type":"46","updated_time":"1355267419","with_tags":""},{"actor_id":"1548840395","post_id":"1548840395_477497642302862","comment_info":{"can_comment":"1","comment_count":"3","comment_order":"chronological"},"created_time":"1355223116","is_popular":"","likes":{"href":"https:\/\/www.facebook.com\/browse\/likes\/?id=477497642302862","count":"2","sample":["100002029008286"],"friends":["1745385892"],"user_likes":"0","can_like":"1"},"permalink":"https:\/\/www.facebook.com\/fra.poco\/posts\/477497642302862","privacy":{"value":""},"share_count":"0","source_id":"1548840395","tagged_ids":"","type":"80","updated_time":"1355252318","with_tags":""},{"actor_id":"1548840395","post_id":"1548840395_10200169218343707","comment_info":{"can_comment":"1","comment_count":"0","comment_order":"chronological"},"created_time":"1355178777","is_popular":"","likes":{"href":"https:\/\/www.facebook.com\/browse\/likes\/?id=10200169218223704","count":"1","sample":"","friends":["1347703224"],"user_likes":"0","can_like":"1"},"permalink":"https:\/\/www.facebook.com\/photo.php?fbid=10200169218223704&set=a.3058819720008.151248.1548840395&type=1&relevant_count=1","privacy":{"value":""},"share_count":"0","source_id":"1548840395","tagged_ids":"","type":"","updated_time":"1355178777","with_tags":""},{"actor_id":"524972083","post_id":"1548840395_10200169199383233","comment_info":{"can_comment":"1","comment_count":"1","comment_order":"chronological"},"created_time":"1355178537","is_popular":"","likes":{"href":"https:\/\/www.facebook.com\/browse\/likes\/?id=10200169199383233","count":"0","sample":"","friends":"","user_likes":"0","can_like":"1"},"permalink":"https:\/\/www.facebook.com\/fra.poco\/posts\/10200169199383233","privacy":{"value":""},"share_count":"0","source_id":"1548840395","tagged_ids":"","type":"","updated_time":"1355178618","with_tags":""},{"actor_id":"1548840395","post_id":"1548840395_10200146394493125","comment_info":{"can_comment":"1","comment_count":"0","comment_order":"chronological"},"created_time":"1354813087","is_popular":"","likes":{"href":"https:\/\/www.facebook.com\/browse\/likes\/?id=10200146394493125","count":"1","sample":["100004746398647"],"friends":"","user_likes":"0","can_like":"1"},"permalink":"https:\/\/www.facebook.com\/fra.poco\/posts\/10200146394493125","privacy":{"value":""},"share_count":"0","source_id":"1548840395","tagged_ids":"","type":"46","updated_time":"1354813087","with_tags":""},{"actor_id":"1548840395","post_id":"1548840395_10200137042859340","comment_info":{"can_comment":"1","comment_count":"3","comment_order":"chronological"},"created_time":"1354659680","is_popular":"","likes":{"href":"https:\/\/www.facebook.com\/browse\/likes\/?id=10200137042859340","count":"1","sample":["100001695783549"],"friends":"","user_likes":"0","can_like":"1"},"permalink":"https:\/\/www.facebook.com\/fra.poco\/posts\/10200137042859340","privacy":{"value":""},"share_count":"0","source_id":"1548840395","tagged_ids":"","type":"46","updated_time":"1354812926","with_tags":""},{"actor_id":"1548840395","post_id":"1548840395_381286865296915","comment_info":{"can_comment":"1","comment_count":"0","comment_order":"chronological"},"created_time":"1354470738","is_popular":"","likes":{"href":"https:\/\/www.facebook.com\/browse\/likes\/?id=381286865296915","count":"1","sample":["100003348410937"],"friends":"","user_likes":"0","can_like":"1"},"permalink":"https:\/\/www.facebook.com\/fra.poco\/posts\/381286865296915","privacy":{"value":""},"share_count":"0","source_id":"1548840395","tagged_ids":"","type":"80","updated_time":"1354470738","with_tags":""},{"actor_id":"1548840395","post_id":"1548840395_463820033659092","comment_info":{"can_comment":"1","comment_count":"0","comment_order":"chronological"},"created_time":"1354394430","is_popular":"","likes":{"href":"https:\/\/www.facebook.com\/browse\/likes\/?id=463820033659092","count":"0","sample":"","friends":"","user_likes":"0","can_like":"1"},"permalink":"https:\/\/www.facebook.com\/fra.poco\/posts\/463820033659092","privacy":{"value":""},"share_count":"0","source_id":"1548840395","tagged_ids":"","type":"80","updated_time":"1354394430","with_tags":""},{"actor_id":"524972083","post_id":"1548840395_10200118614838651","comment_info":{"can_comment":"1","comment_count":"1","comment_order":"chronological"},"created_time":"1354373267","is_popular":"","likes":{"href":"https:\/\/www.facebook.com\/browse\/likes\/?id=10200118614838651","count":"0","sample":"","friends":"","user_likes":"0","can_like":"1"},"permalink":"https:\/\/www.facebook.com\/fra.poco\/posts\/10200118614838651","privacy":{"value":""},"share_count":"0","source_id":"1548840395","tagged_ids":"","type":"","updated_time":"1354373455","with_tags":""},{"actor_id":"1548840395","post_id":"1548840395_435327523193983","comment_info":{"can_comment":"1","comment_count":"0","comment_order":"chronological"},"created_time":"1354284522","is_popular":"","likes":{"href":"https:\/\/www.facebook.com\/browse\/likes\/?id=435327523193983","count":"0","sample":"","friends":"","user_likes":"0","can_like":"1"},"permalink":"https:\/\/www.facebook.com\/fra.poco\/posts\/435327523193983","privacy":{"value":""},"share_count":"0","source_id":"1548840395","tagged_ids":"","type":"80","updated_time":"1354284522","with_tags":""},{"actor_id":"1548840395","post_id":"1548840395_4999382152856","comment_info":{"can_comment":"1","comment_count":"0","comment_order":"chronological"},"created_time":"1353883452","is_popular":"","likes":{"href":"https:\/\/www.facebook.com\/browse\/likes\/?id=4999382152856","count":"1","sample":["100003348410937"],"friends":"","user_likes":"0","can_like":"1"},"permalink":"https:\/\/www.facebook.com\/fra.poco\/posts\/4999382152856","privacy":{"value":""},"share_count":"0","source_id":"1548840395","tagged_ids":"","type":"46","updated_time":"1353883452","with_tags":""},{"actor_id":"1548840395","post_id":"1548840395_4996097950753","comment_info":{"can_comment":"1","comment_count":"6","comment_order":"chronological"},"created_time":"1353836942","is_popular":"","likes":{"href":"https:\/\/www.facebook.com\/browse\/likes\/?id=4996097950753","count":"2","sample":["100003348410937","524972083"],"friends":"","user_likes":"0","can_like":"1"},"permalink":"https:\/\/www.facebook.com\/fra.poco\/posts\/4996097950753","privacy":{"value":""},"share_count":"0","source_id":"1548840395","tagged_ids":"","type":"46","updated_time":"1353843709","with_tags":""},{"actor_id":"1548840395","post_id":"1548840395_175262802614301","comment_info":{"can_comment":"1","comment_count":"0","comment_order":"chronological"},"created_time":"1353787142","is_popular":"","likes":{"href":"https:\/\/www.facebook.com\/browse\/likes\/?id=175262802614301","count":"1","sample":["100003348410937"],"friends":"","user_likes":"0","can_like":"1"},"permalink":"https:\/\/www.facebook.com\/fra.poco\/posts\/175262802614301","privacy":{"value":""},"share_count":"0","source_id":"1548840395","tagged_ids":"","type":"80","updated_time":"1353787142","with_tags":""},{"actor_id":"1548840395","post_id":"1548840395_4969896135724","comment_info":{"can_comment":"1","comment_count":"2","comment_order":"chronological"},"created_time":"1353452205","is_popular":"","likes":{"href":"https:\/\/www.facebook.com\/browse\/likes\/?id=4969896135724","count":"0","sample":"","friends":"","user_likes":"0","can_like":"1"},"permalink":"https:\/\/www.facebook.com\/fra.poco\/posts\/4969896135724","privacy":{"value":""},"share_count":"0","source_id":"1548840395","tagged_ids":"","type":"46","updated_time":"1353452448","with_tags":""},{"actor_id":"1548840395","post_id":"1548840395_4958739936826","comment_info":{"can_comment":"1","comment_count":"0","comment_order":"chronological"},"created_time":"1353274398","is_popular":"","likes":{"href":"https:\/\/www.facebook.com\/browse\/likes\/?id=4958739936826","count":"1","sample":["100003348410937"],"friends":"","user_likes":"0","can_like":"1"},"permalink":"https:\/\/www.facebook.com\/fra.poco\/posts\/4958739936826","privacy":{"value":""},"share_count":"0","source_id":"1548840395","tagged_ids":"","type":"46","updated_time":"1353274398","with_tags":""},{"actor_id":"1548840395","post_id":"1548840395_512377068787675","comment_info":{"can_comment":"1","comment_count":"0","comment_order":"chronological"},"created_time":"1353162004","is_popular":"","likes":{"href":"https:\/\/www.facebook.com\/browse\/likes\/?id=512377068787675","count":"0","sample":"","friends":"","user_likes":"0","can_like":"1"},"permalink":"https:\/\/www.facebook.com\/fra.poco\/posts\/512377068787675","privacy":{"value":""},"share_count":"0","source_id":"1548840395","tagged_ids":"","type":"80","updated_time":"1353162004","with_tags":""},{"actor_id":"1347703224","post_id":"1548840395_4950487250514","comment_info":{"can_comment":"1","comment_count":"2","comment_order":"chronological"},"created_time":"1353144711","is_popular":"","likes":{"href":"https:\/\/www.facebook.com\/browse\/likes\/?id=4950487250514","count":"1","sample":"","friends":["1548840395"],"user_likes":"0","can_like":"1"},"permalink":"https:\/\/www.facebook.com\/fra.poco\/posts\/4950487250514","privacy":{"value":""},"share_count":"0","source_id":"1548840395","tagged_ids":"","type":"","updated_time":"1353172313","with_tags":""},{"actor_id":"1548840395","post_id":"1548840395_371657406258794","comment_info":{"can_comment":"1","comment_count":"0","comment_order":"chronological"},"created_time":"1353081665","is_popular":"","likes":{"href":"https:\/\/www.facebook.com\/browse\/likes\/?id=371657406258794","count":"1","sample":["1437950283"],"friends":"","user_likes":"0","can_like":"1"},"permalink":"https:\/\/www.facebook.com\/fra.poco\/posts\/371657406258794","privacy":{"value":""},"share_count":"0","source_id":"1548840395","tagged_ids":"","type":"80","updated_time":"1353081665","with_tags":""},{"actor_id":"1548840395","post_id":"1548840395_4923027484037","comment_info":{"can_comment":"1","comment_count":"0","comment_order":"chronological"},"created_time":"1352757844","is_popular":"","likes":{"href":"https:\/\/www.facebook.com\/browse\/likes\/?id=4923027484037","count":"1","sample":["100003348410937"],"friends":"","user_likes":"0","can_like":"1"},"permalink":"https:\/\/www.facebook.com\/fra.poco\/posts\/4923027484037","privacy":{"value":""},"share_count":"0","source_id":"1548840395","tagged_ids":"","type":"46","updated_time":"1352757844","with_tags":""},{"actor_id":"1548840395","post_id":"1548840395_4911273950206","comment_info":{"can_comment":"1","comment_count":"1","comment_order":"chronological"},"created_time":"1352566789","is_popular":"","likes":{"href":"https:\/\/www.facebook.com\/browse\/likes\/?id=4911273950206","count":"1","sample":["100003348410937"],"friends":"","user_likes":"0","can_like":"1"},"permalink":"https:\/\/www.facebook.com\/fra.poco\/posts\/4911273950206","privacy":{"value":""},"share_count":"0","source_id":"1548840395","tagged_ids":"","type":"46","updated_time":"1352580563","with_tags":""},{"actor_id":"1548840395","post_id":"1548840395_4907323291442","comment_info":{"can_comment":"1","comment_count":"9","comment_order":"chronological"},"created_time":"1352488678","is_popular":"","likes":{"href":"https:\/\/www.facebook.com\/browse\/likes\/?id=4907323291442","count":"0","sample":"","friends":"","user_likes":"0","can_like":"1"},"permalink":"https:\/\/www.facebook.com\/fra.poco\/posts\/4907323291442","privacy":{"value":""},"share_count":"0","source_id":"1548840395","tagged_ids":"","type":"46","updated_time":"1352490708","with_tags":""},{"actor_id":"1548840395","post_id":"1548840395_4887536996797","comment_info":{"can_comment":"1","comment_count":"22","comment_order":"chronological"},"created_time":"1352154550","is_popular":"","likes":{"href":"https:\/\/www.facebook.com\/browse\/likes\/?id=4887536996797","count":"0","sample":"","friends":"","user_likes":"0","can_like":"1"},"permalink":"https:\/\/www.facebook.com\/fra.poco\/posts\/4887536996797","privacy":{"value":""},"share_count":"0","source_id":"1548840395","tagged_ids":"","type":"46","updated_time":"1352490671","with_tags":""},{"actor_id":"1548840395","post_id":"1548840395_4858040819411","comment_info":{"can_comment":"1","comment_count":"0","comment_order":"chronological"},"created_time":"1351723952","is_popular":"","likes":{"href":"https:\/\/www.facebook.com\/browse\/likes\/?id=4858040819411","count":"0","sample":"","friends":"","user_likes":"0","can_like":"1"},"permalink":"https:\/\/www.facebook.com\/fra.poco\/posts\/4858040819411","privacy":{"value":""},"share_count":"0","source_id":"1548840395","tagged_ids":"","type":"46","updated_time":"1351723952","with_tags":""},{"actor_id":"1548840395","post_id":"1548840395_4855598958366","comment_info":{"can_comment":"1","comment_count":"0","comment_order":"chronological"},"created_time":"1351694259","is_popular":"","likes":{"href":"https:\/\/www.facebook.com\/browse\/likes\/?id=4855598958366","count":"1","sample":["100003348410937"],"friends":"","user_likes":"0","can_like":"1"},"permalink":"https:\/\/www.facebook.com\/fra.poco\/posts\/4855598958366","privacy":{"value":""},"share_count":"0","source_id":"1548840395","tagged_ids":"","type":"46","updated_time":"1351694259","with_tags":""},{"actor_id":"1548840395","post_id":"1548840395_4851969827640","comment_info":{"can_comment":"1","comment_count":"0","comment_order":"chronological"},"created_time":"1351634178","is_popular":"","likes":{"href":"https:\/\/www.facebook.com\/browse\/likes\/?id=4851969827640","count":"1","sample":["100000281172494"],"friends":"","user_likes":"0","can_like":"1"},"permalink":"https:\/\/www.facebook.com\/fra.poco\/posts\/4851969827640","privacy":{"value":""},"share_count":"0","source_id":"1548840395","tagged_ids":"","type":"46","updated_time":"1351634178","with_tags":""},{"actor_id":"1548840395","post_id":"1548840395_165148326942677","comment_info":{"can_comment":"1","comment_count":"0","comment_order":"chronological"},"created_time":"1351629352","is_popular":"","likes":{"href":"https:\/\/www.facebook.com\/browse\/likes\/?id=165148326942677","count":"1","sample":["100003348410937"],"friends":"","user_likes":"0","can_like":"1"},"permalink":"https:\/\/www.facebook.com\/fra.poco\/posts\/165148326942677","privacy":{"value":""},"share_count":"0","source_id":"1548840395","tagged_ids":"","type":"80","updated_time":"1351629352","with_tags":""},{"actor_id":"1548840395","post_id":"1548840395_4840065730045","comment_info":{"can_comment":"1","comment_count":"6","comment_order":"chronological"},"created_time":"1351463408","is_popular":"","likes":{"href":"https:\/\/www.facebook.com\/browse\/likes\/?id=4840065730045","count":"0","sample":"","friends":"","user_likes":"0","can_like":"1"},"permalink":"https:\/\/www.facebook.com\/fra.poco\/posts\/4840065730045","privacy":{"value":""},"share_count":"0","source_id":"1548840395","tagged_ids":"","type":"46","updated_time":"1351464077","with_tags":""},{"actor_id":"1548840395","post_id":"1548840395_4826341466947","comment_info":{"can_comment":"1","comment_count":"5","comment_order":"chronological"},"created_time":"1351266886","is_popular":"","likes":{"href":"https:\/\/www.facebook.com\/browse\/likes\/?id=4826341466947","count":"1","sample":["524972083"],"friends":"","user_likes":"0","can_like":"1"},"permalink":"https:\/\/www.facebook.com\/fra.poco\/posts\/4826341466947","privacy":{"value":""},"share_count":"0","source_id":"1548840395","tagged_ids":"","type":"46","updated_time":"1351267440","with_tags":""},{"actor_id":"1548840395","post_id":"1548840395_158451490966138","comment_info":{"can_comment":"1","comment_count":"0","comment_order":"chronological"},"created_time":"1351201150","is_popular":"","likes":{"href":"https:\/\/www.facebook.com\/browse\/likes\/?id=158451490966138","count":"3","sample":["100003348410937","1264811216","1437950283"],"friends":"","user_likes":"0","can_like":"1"},"permalink":"https:\/\/www.facebook.com\/fra.poco\/posts\/158451490966138","privacy":{"value":""},"share_count":"0","source_id":"1548840395","tagged_ids":"","type":"80","updated_time":"1351201150","with_tags":""},{"actor_id":"1548840395","post_id":"1548840395_4816732066718","comment_info":{"can_comment":"1","comment_count":"0","comment_order":"chronological"},"created_time":"1351114529","is_popular":"","likes":{"href":"https:\/\/www.facebook.com\/browse\/likes\/?id=4816732066718","count":"0","sample":"","friends":"","user_likes":"0","can_like":"1"},"permalink":"https:\/\/www.facebook.com\/fra.poco\/posts\/4816732066718","privacy":{"value":""},"share_count":"0","source_id":"1548840395","tagged_ids":"","type":"46","updated_time":"1351114529","with_tags":""},{"actor_id":"1548840395","post_id":"1548840395_276156505837883","comment_info":{"can_comment":"1","comment_count":"0","comment_order":"chronological"},"created_time":"1351085782","is_popular":"","likes":{"href":"https:\/\/www.facebook.com\/browse\/likes\/?id=276156505837883","count":"0","sample":"","friends":"","user_likes":"0","can_like":"1"},"permalink":"https:\/\/www.facebook.com\/fra.poco\/posts\/276156505837883","privacy":{"value":""},"share_count":"0","source_id":"1548840395","tagged_ids":"","type":"80","updated_time":"1351085782","with_tags":""},{"actor_id":"1548840395","post_id":"1548840395_4811126886592","comment_info":{"can_comment":"1","comment_count":"12","comment_order":"chronological"},"created_time":"1351028896","is_popular":"","likes":{"href":"https:\/\/www.facebook.com\/browse\/likes\/?id=4811126486582","count":"2","sample":["100001695783549"],"friends":["1745385892"],"user_likes":"0","can_like":"1"},"permalink":"https:\/\/www.facebook.com\/photo.php?fbid=4811126486582&set=a.4811126446581.186543.1548840395&type=1","privacy":{"value":""},"share_count":"0","source_id":"1548840395","tagged_ids":"","type":"247","updated_time":"1351103092","with_tags":""},{"actor_id":"1548840395","post_id":"1548840395_4805233459260","comment_info":{"can_comment":"1","comment_count":"1","comment_order":"chronological"},"created_time":"1350938620","is_popular":"","likes":{"href":"https:\/\/www.facebook.com\/browse\/likes\/?id=4805233459260","count":"1","sample":["100003348410937"],"friends":"","user_likes":"0","can_like":"1"},"permalink":"https:\/\/www.facebook.com\/fra.poco\/posts\/4805233459260","privacy":{"value":""},"share_count":"0","source_id":"1548840395","tagged_ids":"","type":"46","updated_time":"1350942419","with_tags":""},{"actor_id":"1548840395","post_id":"1548840395_4799685360561","comment_info":{"can_comment":"1","comment_count":"0","comment_order":"chronological"},"created_time":"1350853516","is_popular":"","likes":{"href":"https:\/\/www.facebook.com\/browse\/likes\/?id=4799685360561","count":"1","sample":["100003348410937"],"friends":"","user_likes":"0","can_like":"1"},"permalink":"https:\/\/www.facebook.com\/fra.poco\/posts\/4799685360561","privacy":{"value":""},"share_count":"0","source_id":"1548840395","tagged_ids":"","type":"46","updated_time":"1350853516","with_tags":""},{"actor_id":"1548840395","post_id":"1548840395_4791527356616","comment_info":{"can_comment":"1","comment_count":"0","comment_order":"chronological"},"created_time":"1350730094","is_popular":"","likes":{"href":"https:\/\/www.facebook.com\/browse\/likes\/?id=4791527356616","count":"1","sample":"","friends":["100002888949752"],"user_likes":"0","can_like":"1"},"permalink":"https:\/\/www.facebook.com\/fra.poco\/posts\/4791527356616","privacy":{"value":""},"share_count":"0","source_id":"1548840395","tagged_ids":"","type":"46","updated_time":"1350730094","with_tags":""},{"actor_id":"1548840395","post_id":"1548840395_4752294295814","comment_info":{"can_comment":"1","comment_count":"0","comment_order":"chronological"},"created_time":"1350076990","is_popular":"","likes":{"href":"https:\/\/www.facebook.com\/browse\/likes\/?id=4752294295814","count":"1","sample":["100003348410937"],"friends":"","user_likes":"0","can_like":"1"},"permalink":"https:\/\/www.facebook.com\/fra.poco\/posts\/4752294295814","privacy":{"value":""},"share_count":"0","source_id":"1548840395","tagged_ids":"","type":"46","updated_time":"1350076990","with_tags":""},{"actor_id":"1548840395","post_id":"1548840395_4740828009164","comment_info":{"can_comment":"1","comment_count":"0","comment_order":"chronological"},"created_time":"1349905788","is_popular":"","likes":{"href":"https:\/\/www.facebook.com\/browse\/likes\/?id=4740828009164","count":"1","sample":["100003348410937"],"friends":"","user_likes":"0","can_like":"1"},"permalink":"https:\/\/www.facebook.com\/fra.poco\/posts\/4740828009164","privacy":{"value":""},"share_count":"0","source_id":"1548840395","tagged_ids":"","type":"46","updated_time":"1349905788","with_tags":""},{"actor_id":"594679098","post_id":"1548840395_499529706737582","comment_info":{"can_comment":"1","comment_count":"3","comment_order":"chronological"},"created_time":"1349718581","is_popular":"","likes":{"href":"https:\/\/www.facebook.com\/browse\/likes\/?id=499529706737582","count":"0","sample":"","friends":"","user_likes":"0","can_like":"1"},"permalink":"https:\/\/www.facebook.com\/fra.poco\/posts\/499529706737582","privacy":{"value":""},"share_count":"0","source_id":"1548840395","tagged_ids":"","type":"","updated_time":"1349725744","with_tags":""},{"actor_id":"1548840395","post_id":"1548840395_4722673155304","comment_info":{"can_comment":"1","comment_count":"0","comment_order":"chronological"},"created_time":"1349643913","is_popular":"","likes":{"href":"https:\/\/www.facebook.com\/browse\/likes\/?id=4722673155304","count":"1","sample":["100000281172494"],"friends":"","user_likes":"0","can_like":"1"},"permalink":"https:\/\/www.facebook.com\/fra.poco\/posts\/4722673155304","privacy":{"value":""},"share_count":"0","source_id":"1548840395","tagged_ids":"","type":"46","updated_time":"1349643913","with_tags":""},{"actor_id":"1548840395","post_id":"1548840395_390204941051110","comment_info":{"can_comment":"1","comment_count":"1","comment_order":"chronological"},"created_time":"1349543145","is_popular":"","likes":{"href":"https:\/\/www.facebook.com\/browse\/likes\/?id=390204941051110","count":"1","sample":["100003348410937"],"friends":"","user_likes":"0","can_like":"1"},"permalink":"https:\/\/www.facebook.com\/fra.poco\/posts\/390204941051110","privacy":{"value":""},"share_count":"0","source_id":"1548840395","tagged_ids":"","type":"80","updated_time":"1349552668","with_tags":""},{"actor_id":"100001695783549","post_id":"1548840395_4703870605252","comment_info":{"can_comment":"1","comment_count":"1","comment_order":"chronological"},"created_time":"1349351309","is_popular":"","likes":{"href":"https:\/\/www.facebook.com\/browse\/likes\/?id=4703870605252","count":"0","sample":"","friends":"","user_likes":"0","can_like":"1"},"permalink":"https:\/\/www.facebook.com\/fra.poco\/posts\/4703870605252","privacy":{"value":""},"share_count":"0","source_id":"1548840395","tagged_ids":"","type":"","updated_time":"1349355809","with_tags":""},{"actor_id":"100002888949752","post_id":"1548840395_4703090305745","comment_info":{"can_comment":"1","comment_count":"6","comment_order":"chronological"},"created_time":"1349335684","is_popular":"","likes":{"href":"https:\/\/www.facebook.com\/browse\/likes\/?id=4703090305745","count":"1","sample":"","friends":["1745385892"],"user_likes":"0","can_like":"1"},"permalink":"https:\/\/www.facebook.com\/fra.poco\/posts\/4703090305745","privacy":{"value":""},"share_count":"0","source_id":"1548840395","tagged_ids":"","type":"","updated_time":"1349355800","with_tags":""},{"actor_id":"1548840395","post_id":"1548840395_4681741532039","comment_info":{"can_comment":"1","comment_count":"2","comment_order":"chronological"},"created_time":"1348990968","is_popular":"","likes":{"href":"https:\/\/www.facebook.com\/browse\/likes\/?id=4681741532039","count":"1","sample":"","friends":["1745385892"],"user_likes":"0","can_like":"1"},"permalink":"https:\/\/www.facebook.com\/fra.poco\/posts\/4681741532039","privacy":{"value":""},"share_count":"0","source_id":"1548840395","tagged_ids":"","type":"46","updated_time":"1348991257","with_tags":""},{"actor_id":"1548840395","post_id":"1548840395_354780657944675","comment_info":{"can_comment":"1","comment_count":"0","comment_order":"chronological"},"created_time":"1348941441","is_popular":"","likes":{"href":"https:\/\/www.facebook.com\/browse\/likes\/?id=354780657944675","count":"1","sample":["710769094"],"friends":"","user_likes":"0","can_like":"1"},"permalink":"https:\/\/www.facebook.com\/fra.poco\/posts\/354780657944675","privacy":{"value":""},"share_count":"0","source_id":"1548840395","tagged_ids":"","type":"80","updated_time":"1348941441","with_tags":""},{"actor_id":"1548840395","post_id":"1548840395_4675348972229","comment_info":{"can_comment":"1","comment_count":"0","comment_order":"chronological"},"created_time":"1348870920","is_popular":"","likes":{"href":"https:\/\/www.facebook.com\/browse\/likes\/?id=4675348972229","count":"2","sample":["1061947570","524972083"],"friends":"","user_likes":"0","can_like":"1"},"permalink":"https:\/\/www.facebook.com\/fra.poco\/posts\/4675348972229","privacy":{"value":""},"share_count":"0","source_id":"1548840395","tagged_ids":"","type":"46","updated_time":"1348870920","with_tags":""},{"actor_id":"1548840395","post_id":"1548840395_4669720231514","comment_info":{"can_comment":"1","comment_count":"0","comment_order":"chronological"},"created_time":"1348782089","is_popular":"","likes":{"href":"https:\/\/www.facebook.com\/browse\/likes\/?id=4669720231514","count":"1","sample":["100001695783549"],"friends":"","user_likes":"0","can_like":"1"},"permalink":"https:\/\/www.facebook.com\/fra.poco\/posts\/4669720231514","privacy":{"value":""},"share_count":"0","source_id":"1548840395","tagged_ids":"","type":"46","updated_time":"1348782089","with_tags":""},{"actor_id":"1548840395","post_id":"1548840395_4663666360171","comment_info":{"can_comment":"1","comment_count":"2","comment_order":"chronological"},"created_time":"1348688834","is_popular":"","likes":{"href":"https:\/\/www.facebook.com\/browse\/likes\/?id=4663666360171","count":"0","sample":"","friends":"","user_likes":"0","can_like":"1"},"permalink":"https:\/\/www.facebook.com\/fra.poco\/posts\/4663666360171","privacy":{"value":""},"share_count":"0","source_id":"1548840395","tagged_ids":"","type":"46","updated_time":"1348689037","with_tags":""},{"actor_id":"1548840395","post_id":"1548840395_4659222489077","comment_info":{"can_comment":"1","comment_count":"0","comment_order":"chronological"},"created_time":"1348613216","is_popular":"","likes":{"href":"https:\/\/www.facebook.com\/browse\/likes\/?id=4659222489077","count":"1","sample":["100003348410937"],"friends":"","user_likes":"0","can_like":"1"},"permalink":"https:\/\/www.facebook.com\/fra.poco\/posts\/4659222489077","privacy":{"value":""},"share_count":"0","source_id":"1548840395","tagged_ids":"","type":"46","updated_time":"1348613216","with_tags":""},{"actor_id":"1548840395","post_id":"1548840395_443108605735907","comment_info":{"can_comment":"1","comment_count":"0","comment_order":"chronological"},"created_time":"1348231382","is_popular":"","likes":{"href":"https:\/\/www.facebook.com\/browse\/likes\/?id=443108605735907","count":"0","sample":"","friends":"","user_likes":"0","can_like":"1"},"permalink":"https:\/\/www.facebook.com\/fra.poco\/posts\/443108605735907","privacy":{"value":""},"share_count":"0","source_id":"1548840395","tagged_ids":"","type":"80","updated_time":"1348231382","with_tags":""},{"actor_id":"1548840395","post_id":"1548840395_4627475575424","comment_info":{"can_comment":"1","comment_count":"3","comment_order":"chronological"},"created_time":"1348091483","is_popular":"","likes":{"href":"https:\/\/www.facebook.com\/browse\/likes\/?id=4627475575424","count":"0","sample":"","friends":"","user_likes":"0","can_like":"1"},"permalink":"https:\/\/www.facebook.com\/fra.poco\/posts\/4627475575424","privacy":{"value":""},"share_count":"0","source_id":"1548840395","tagged_ids":"","type":"46","updated_time":"1348144444","with_tags":""},{"actor_id":"1548840395","post_id":"1548840395_4605068255255","comment_info":{"can_comment":"1","comment_count":"0","comment_order":"chronological"},"created_time":"1347745762","is_popular":"","likes":{"href":"https:\/\/www.facebook.com\/browse\/likes\/?id=4605068255255","count":"1","sample":["100003348410937"],"friends":"","user_likes":"0","can_like":"1"},"permalink":"https:\/\/www.facebook.com\/fra.poco\/posts\/4605068255255","privacy":{"value":""},"share_count":"0","source_id":"1548840395","tagged_ids":"","type":"46","updated_time":"1347745762","with_tags":""},{"actor_id":"1548840395","post_id":"1548840395_4605067495236","comment_info":{"can_comment":"1","comment_count":"0","comment_order":"chronological"},"created_time":"1347745741","is_popular":"","likes":{"href":"https:\/\/www.facebook.com\/browse\/likes\/?id=4605067495236","count":"0","sample":"","friends":"","user_likes":"0","can_like":"1"},"permalink":"https:\/\/www.facebook.com\/fra.poco\/posts\/4605067495236","privacy":{"value":""},"share_count":"0","source_id":"1548840395","tagged_ids":"","type":"46","updated_time":"1347745741","with_tags":""},{"actor_id":"1548840395","post_id":"1548840395_4596429559293","comment_info":{"can_comment":"1","comment_count":"0","comment_order":"chronological"},"created_time":"1347571599","is_popular":"","likes":{"href":"https:\/\/www.facebook.com\/browse\/likes\/?id=4596429559293","count":"1","sample":["100002029008286"],"friends":"","user_likes":"0","can_like":"1"},"permalink":"https:\/\/www.facebook.com\/fra.poco\/posts\/4596429559293","privacy":{"value":""},"share_count":"0","source_id":"1548840395","tagged_ids":"","type":"46","updated_time":"1347571599","with_tags":""},{"actor_id":"1548840395","post_id":"1548840395_482307941792915","comment_info":{"can_comment":"1","comment_count":"1","comment_order":"chronological"},"created_time":"1347486516","is_popular":"","likes":{"href":"https:\/\/www.facebook.com\/browse\/likes\/?id=482307941792915","count":"0","sample":"","friends":"","user_likes":"0","can_like":"1"},"permalink":"https:\/\/www.facebook.com\/fra.poco\/posts\/482307941792915","privacy":{"value":""},"share_count":"0","source_id":"1548840395","tagged_ids":"","type":"80","updated_time":"1347827429","with_tags":""},{"actor_id":"524972083","post_id":"1548840395_4591894725925","comment_info":{"can_comment":"1","comment_count":"10","comment_order":"chronological"},"created_time":"1347483548","is_popular":"","likes":{"href":"https:\/\/www.facebook.com\/browse\/likes\/?id=4591894725925","count":"0","sample":"","friends":"","user_likes":"0","can_like":"1"},"permalink":"https:\/\/www.facebook.com\/fra.poco\/posts\/4591894725925","privacy":{"value":""},"share_count":"0","source_id":"1548840395","tagged_ids":"","type":"","updated_time":"1347485432","with_tags":""}]
